{
  "en": {
    "translation": {
      "GAME_TITLE": "The Imposter",
      "TAGLINE": "Who is among us?",
      "LANGUAGE_SELECT": "Select Language",
      "NEW_GAME": "New Game",
      "HOW_TO_PLAY": "How to Play",
      "HOW_TITLE": "How to Play",
      "HOW_STEP1_TITLE": "Setup",
      "HOW_STEP1_DESC": "Enter 3-8 player names and choose a category.",
      "HOW_STEP2_TITLE": "Reveal Roles",
      "HOW_STEP2_DESC": "Pass the phone to each player. One player is the Imposter and does NOT see the subject!",
      "HOW_STEP3_TITLE": "Ask Questions",
      "HOW_STEP3_DESC": "Players take turns asking each other Yes/No questions about the subject. The Imposter bluffs!",
      "HOW_STEP4_TITLE": "Vote",
      "HOW_STEP4_DESC": "Everyone secretly votes for who they think is the Imposter. You cannot vote for yourself — unless Hard Mode is on!",
      "HOW_STEP5_TITLE": "Score",
      "HOW_STEP5_DESC": "Correctly guess the Imposter = +100 pts. Imposter guesses the subject = +100 pts. Imposter fools everyone = +200 bonus (normal mode only). Hard Mode: Imposter self-vote = +100 pts; no fooled-all bonus.",
      "BACK": "Back",
      "CONTINUE": "Continue",
      "DONE": "Got it!",
      "SETUP_TITLE": "Game Setup",
      "ADD_PLAYER": "+ Add Player",
      "REMOVE_PLAYER": "Remove Last",
      "PLAYER_N": "Player {n}",
      "PLAYER_NAME_HINT": "Player name...",
      "PLAYERS_LABEL": "Players ({count})",
      "MIN_PLAYERS_WARNING": "Need at least 3 players!",
      "EMPTY_NAME_WARNING": "All player names must be filled in!",
      "DUPLICATE_NAME_WARNING": "No two players can have the same name!",
      "HARD_MODE": "Hard Mode",
      "HARD_MODE_HINT": "Imposter sees a fake subject — nobody knows who they are!",
      "SELECT_CATEGORY": "Choose a Category",
      "START_GAME": "Start Game!",
      "PASS_TO": "Pass to {name}",
      "TAP_TO_REVEAL": "Tap to See Your Role",
      "PLAYER_X_OF_Y": "Player {current} of {total}",
      "PRIVACY_NOTE": "Don't show to others!",
      "YOU_ARE_IMPOSTER": "You are the\nIMPOSTER!",
      "IMPOSTER_DESCRIPTION": "You don't know the subject. Ask clever questions and don't get caught!",
      "YOU_KNOW_SUBJECT": "The subject is:",
      "REMEMBER_SUBJECT": "Remember it! Don't say it out loud.",
      "QUESTION_PHASE_TITLE": "Question Time",
      "QUESTION_COUNT": "Question {current} of {total}",
      "PLAYER_ASKS": "{asker} asks {answerer}",
      "ASK_INSTRUCTIONS": "Ask a Yes/No question about the subject",
      "NEXT_QUESTION": "Next Question",
      "FINISH_QUESTIONS": "End Questions & Vote",
      "VOTING_TITLE": "Vote for the Imposter",
      "VOTING_PLAYER": "{name}, who is the Imposter?",
      "VOTING_INSTRUCTIONS": "Who is the IMPOSTER? Tap their name to vote!",
      "VOTE_SUBMIT": "Cast My Vote",
      "REVEAL_TITLE": "The Imposter is…",
      "CORRECT_VOTERS": "Correctly Identified",
      "INCORRECT_VOTERS": "Fooled By Imposter",
      "NOBODY_GUESSED": "Nobody caught the Imposter! +200 bonus!",
      "GUESS_TITLE": "Imposter's Last Stand",
      "PASS_TO_IMPOSTER": "Pass to {name} (the Imposter)",
      "GUESS_INSTRUCTIONS": "What was the subject everyone was talking about?",
      "SUBMIT_GUESS": "Submit Guess",
      "GUESS_CORRECT": "Correct! +100 points!",
      "GUESS_WRONG": "Wrong! The subject was: {subject}",
      "SUMMARY_TITLE": "Round {round} Summary",
      "SCORES_TITLE": "Scoreboard",
      "NEXT_ROUND": "Next Round",
      "END_GAME": "End Game",
      "WINNER_IS": "Leading: {name}",
      "CAT_RANDOM": "🎲 Random",
      "CAT_FOOD": "🍕 Food",
      "CAT_ANIMALS": "🦁 Animals",
      "CAT_COUNTRIES": "🌍 Countries",
      "CAT_SPORTS": "⚽ Sports",
      "CAT_VEHICLES": "✈️ Vehicles",
      "CAT_CLOTHING": "👗 Clothing",
      "CAT_NATURE": "🌈 Nature",
      "CAT_MOVIES": "🎬 Movies",
      "CAT_MUSIC": "🎵 Music",
      "CAT_CUSTOM": "✏️ Custom",
      "SETTINGS": "Settings",
      "MUSIC_ON": "♫ Music: ON",
      "MUSIC_OFF": "✕ Music: OFF",
      "CUSTOM_SUBJECTS_HINT": "apple, car, guitar, Paris, ...",
      "CUSTOM_MIN_WARNING": "Enter at least 1 subject!",
      "LOADING_OPTIONS": "Finding options…",
      "SAVED_GAME_FOUND": "Game in progress",
      "RESUME_ROUND_INFO": "Round {round} · {players} players",
      "RESUME_GAME": "▶  Resume",
      "START_FRESH": "New Game",
      "CREDITS": "Credits",
      "QUIT_GAME": "Quit to Menu",
      "QUIT_CONFIRM": "End the current game and start over?",
      "KEEP_PLAYING": "Keep Playing",
      "ASKS_ARROW": "▼  asks  ▼",
      "FUNNY_TAGLINE_1": "Warning: may cause trust issues",
      "FUNNY_TAGLINE_2": "Your friends are probably lying",
      "FUNNY_TAGLINE_3": "Nobody is innocent here",
      "FUNNY_TAGLINE_4": "Suspicion guaranteed",
      "FUNNY_TAGLINE_5": "Friendships tested since 2025",
      "FUNNY_TAGLINE_6": "The impostor is reading this",
      "FUNNY_TAGLINE_7": "100% made-up accusations",
      "FUNNY_TAGLINE_8": "Blame someone. Anyone.",
      "FUNNY_TAGLINE_9": "Even the host is suspicious",
      "FUNNY_TAGLINE_10": "Point fingers. Destroy friendships.",
      "FUNNY_TAGLINE_11": "Side effects include paranoia and cold sweats",
      "FUNNY_TAGLINE_12": "No friendships were harmed in this game... maybe",
      "FUNNY_TAGLINE_13": "Official sponsor of awkward silences",
      "FUNNY_TAGLINE_14": "Eye contact = instant suspicion",
      "FUNNY_TAGLINE_15": "The quiet one did it. Always.",
      "FUNNY_TAGLINE_16": "Poker face required. Results may vary.",
      "FUNNY_TAGLINE_17": "Scientifically proven to ruin game nights",
      "FUNNY_TAGLINE_18": "Trust no one. Not even yourself.",
      "FUNNY_TAGLINE_19": "Lying: the only skill that matters here",
      "FUNNY_TAGLINE_20": "Plot twist incoming. Every. Single. Round.",
      "FUNNY_TAGLINE_21": "Your face is giving you away",
      "FUNNY_TAGLINE_22": "The imposter has already won the staring contest",
      "FUNNY_TAGLINE_23": "Sponsored by 4AM trust issues",
      "FUNNY_TAGLINE_24": "Accusation is just honesty with extra steps",
      "FUNNY_TAGLINE_25": "May contain traces of backstabbing",
      "FUNNY_TAGLINE_26": "Gaslighting your friends, responsibly",
      "FUNNY_TAGLINE_27": "Nobody likes a bad liar. Improve.",
      "FUNNY_TAGLINE_28": "Sweating? Probably the imposter.",
      "FUNNY_TAGLINE_29": "Lies taste better with friends around",
      "FUNNY_TAGLINE_30": "Warning: your poker face is terrible",
      "CUSTOM_COMMA_HINT": "Separate with commas · at least 1 subject",
      "PASS_AND_PLAY": "Pass & Play",
      "LOCAL_MULTIPLAYER": "Local Multiplayer",
      "LAN_CONNECT_HINT": "Play together on the same WiFi or Bluetooth hotspot",
      "LAN_HOST_BUTTON": "Host a Game",
      "LAN_HOST_DESC": "Start a game on this device. Others scan or enter your IP to join.",
      "LAN_JOIN_BUTTON": "Join a Game",
      "LAN_JOIN_DESC": "Find a nearby game automatically or enter the host's IP address.",
      "LAN_HOST_TITLE": "Hosting Game",
      "LAN_HOST_IP_LABEL": "Your IP Address:",
      "LAN_HOST_WAITING": "Waiting for players to join...",
      "LAN_HOST_START_GAME": "Start Game",
      "LAN_HOST_MIN_PLAYERS": "Need at least 3 players to start",
      "LAN_JOIN_TITLE": "Join Game",
      "LAN_JOIN_AUTO_LABEL": "Games Found Nearby",
      "LAN_JOIN_SCANNING": "Scanning for games...",
      "LAN_JOIN_IP_HINT": "Or enter host IP manually",
      "LAN_JOIN_CONNECT": "Connect",
      "LAN_JOIN_CONNECTING": "Connecting...",
      "LAN_JOIN_WAITING": "Connected! Waiting for host to start...",
      "LAN_JOIN_FAILED": "Connection failed. Check the IP and try again.",
      "LAN_AVATAR_TITLE": "Choose Your Avatar",
      "LAN_AVATAR_CONFIRM": "Confirm",
      "LAN_AVATAR_READY_COUNT": "{ready} / {total} ready",
      "LAN_ROLE_REVEAL_TITLE": "Your Role",
      "LAN_ROLE_WAITING": "Waiting for all players...",
      "LAN_QUESTIONS_HOST_HINT": "Tap Next to advance questions",
      "LAN_QUESTIONS_CLIENT_HINT": "Host is controlling the questions",
      "LAN_VOTES_COUNT": "Votes in: {count} / {total}",
      "LAN_REVEAL_CLIENT_WAIT": "Waiting for host to continue...",
      "LAN_GUESS_WAITING": "The imposter is thinking...",
      "LAN_SUMMARY_CLIENT_WAIT": "Waiting for host...",
      "IMPOSTER_FLED_TITLE": "The Imposter Ran Away!",
      "IMPOSTER_FLED_MESSAGE": "{name} has fled the scene like a coward! Everyone gets 100 points!",
      "HOST_LEFT_MESSAGE": "The host has left the game.",
      "QUIT_CONFIRM_LAN": "Leave the multiplayer game? Other players will be affected.",
      "LAN_NAME_LABEL": "Your Name",
      "LAN_BLUETOOTH_TIP": "No WiFi? Enable Bluetooth Hotspot on one device and connect others to it.",
      "CONFIRM_VOTE": "Confirm Vote",
      "CANCEL": "Cancel",
      "YES_FINISH": "Yes, finish",
      "KEEP_THIS": "speed bonus saved",
      "CONFIRM_END_GAME": "End the game?",
      "ROUND_BONUS": "Round Bonus",
      "BONUS_ALL_PLAYERS": "{delta} pts for ALL PLAYERS!",
      "BONUS_FROM_ROUND": "{delta} pts bonus round",
      "LOADING_IMAGE": "Loading image...",
      "TAP_TO_CLOSE": "Tap anywhere to close",
      "HOW_STEP6_TITLE": "Speed Bonus",
      "HOW_STEP6_DESC": "A ⚡ pool of 500 pts drains as you discuss. Finish questions faster to save more bonus — split equally among non-imposters!",
      "HOW_STEP8_TITLE": "Lucky Spin",
      "HOW_STEP8_DESC": "Before every scoreboard, a slot machine spins for ALL players! Win (60% chance): +50 pts each. Lose (40% chance): −50 pts each. Score never drops below 0."
    }
  },
  "ar": {
    "translation": {
      "GAME_TITLE": "المتسلل",
      "TAGLINE": "من هو المتسلل؟",
      "LANGUAGE_SELECT": "اختر اللغة",
      "NEW_GAME": "لعبة جديدة",
      "HOW_TO_PLAY": "كيف تلعب",
      "HOW_TITLE": "كيف تلعب",
      "HOW_STEP1_TITLE": "الإعداد",
      "HOW_STEP1_DESC": "أدخل أسماء 3-8 لاعبين واختر فئة.",
      "HOW_STEP2_TITLE": "كشف الأدوار",
      "HOW_STEP2_DESC": "مرر الهاتف لكل لاعب. لاعب واحد هو المتسلل ولن يرى الموضوع!",
      "HOW_STEP3_TITLE": "طرح الأسئلة",
      "HOW_STEP3_DESC": "يتناوب اللاعبون في طرح أسئلة نعم/لا عن الموضوع. المتسلل يخمّن!",
      "HOW_STEP4_TITLE": "التصويت",
      "HOW_STEP4_DESC": "يصوّت الجميع سراً على من يعتقد أنه المتسلل. لا يمكنك التصويت لنفسك — إلا في الوضع الصعب!",
      "HOW_STEP5_TITLE": "النتائج",
      "HOW_STEP5_DESC": "تخمين المتسلل صحيح = +100 نقطة. المتسلل يعرف الموضوع = +100 نقطة. المتسلل يخدع الجميع = +200 (الوضع العادي فقط). الوضع الصعب: التصويت الذاتي = +100 نقطة؛ لا مكافأة للخداع.",
      "BACK": "رجوع",
      "CONTINUE": "متابعة",
      "DONE": "فهمت!",
      "SETUP_TITLE": "إعداد اللعبة",
      "ADD_PLAYER": "+ إضافة لاعب",
      "REMOVE_PLAYER": "حذف الأخير",
      "PLAYER_N": "لاعب {n}",
      "PLAYER_NAME_HINT": "اسم اللاعب...",
      "PLAYERS_LABEL": "اللاعبون ({count})",
      "MIN_PLAYERS_WARNING": "تحتاج 3 لاعبين على الأقل!",
      "EMPTY_NAME_WARNING": "يجب تعبئة جميع أسماء اللاعبين!",
      "DUPLICATE_NAME_WARNING": "لا يمكن أن يكون لاعبان بنفس الاسم!",
      "HARD_MODE": "الوضع الصعب",
      "HARD_MODE_HINT": "المتسلل يرى موضوعاً مزيفاً — لا أحد يعرف من هو!",
      "SELECT_CATEGORY": "اختر فئة",
      "START_GAME": "ابدأ اللعبة!",
      "PASS_TO": "مرر إلى {name}",
      "TAP_TO_REVEAL": "اضغط لترى دورك",
      "PLAYER_X_OF_Y": "اللاعب {current} من {total}",
      "PRIVACY_NOTE": "لا تُظهر للآخرين!",
      "YOU_ARE_IMPOSTER": "أنت\nالمتسلل!",
      "IMPOSTER_DESCRIPTION": "لا تعرف الموضوع. اطرح أسئلة ذكية ولا تنكشف!",
      "YOU_KNOW_SUBJECT": "الموضوع هو:",
      "REMEMBER_SUBJECT": "تذكره! لا تقله بصوت عالٍ.",
      "QUESTION_PHASE_TITLE": "وقت الأسئلة",
      "QUESTION_COUNT": "السؤال {current} من {total}",
      "PLAYER_ASKS": "{asker} يسأل {answerer}",
      "ASK_INSTRUCTIONS": "اطرح سؤال نعم/لا عن الموضوع",
      "NEXT_QUESTION": "السؤال التالي",
      "FINISH_QUESTIONS": "إنهاء الأسئلة والتصويت",
      "VOTING_TITLE": "صوّت على المتسلل",
      "VOTING_PLAYER": "{name}، من هو المتسلل؟",
      "VOTING_INSTRUCTIONS": "من المتسلل؟ انقر على اسمه للتصويت!",
      "VOTE_SUBMIT": "أدلِ بصوتي",
      "REVEAL_TITLE": "المتسلل هو…",
      "CORRECT_VOTERS": "صوّتوا صحيح",
      "INCORRECT_VOTERS": "خُدعوا بالمتسلل",
      "NOBODY_GUESSED": "لم يكتشف أحد المتسلل! +200 مكافأة!",
      "GUESS_TITLE": "اختبار المتسلل الأخير",
      "PASS_TO_IMPOSTER": "مرر إلى {name} (المتسلل)",
      "GUESS_INSTRUCTIONS": "ما هو الموضوع الذي كان الجميع يتحدث عنه؟",
      "SUBMIT_GUESS": "أرسل تخميني",
      "GUESS_CORRECT": "صحيح! +100 نقطة!",
      "GUESS_WRONG": "خطأ! الموضوع كان: {subject}",
      "SUMMARY_TITLE": "ملخص الجولة {round}",
      "SCORES_TITLE": "لوحة النتائج",
      "NEXT_ROUND": "الجولة التالية",
      "END_GAME": "إنهاء اللعبة",
      "WINNER_IS": "في الصدارة: {name}",
      "CAT_RANDOM": "🎲 عشوائي",
      "CAT_FOOD": "🍕 طعام",
      "CAT_ANIMALS": "🦁 حيوانات",
      "CAT_COUNTRIES": "🌍 دول",
      "CAT_SPORTS": "⚽ رياضة",
      "CAT_VEHICLES": "✈️ مركبات",
      "CAT_CLOTHING": "👗 ملابس",
      "CAT_NATURE": "🌈 طبيعة",
      "CAT_MOVIES": "🎬 أفلام",
      "CAT_MUSIC": "🎵 موسيقى",
      "CAT_CUSTOM": "✏️ مخصص",
      "SETTINGS": "الإعدادات",
      "MUSIC_ON": "♫ الموسيقى: تشغيل",
      "MUSIC_OFF": "✕ الموسيقى: إيقاف",
      "CUSTOM_SUBJECTS_HINT": "تفاحة، سيارة، جيتار، ...",
      "CUSTOM_MIN_WARNING": "أدخل موضوعاً واحداً على الأقل!",
      "LOADING_OPTIONS": "جارٍ البحث عن الخيارات…",
      "SAVED_GAME_FOUND": "لعبة قيد التشغيل",
      "RESUME_ROUND_INFO": "الجولة {round} · {players} لاعبين",
      "RESUME_GAME": "▶  استئناف",
      "START_FRESH": "لعبة جديدة",
      "CREDITS": "الاعتمادات",
      "QUIT_GAME": "الخروج إلى القائمة",
      "QUIT_CONFIRM": "هل تريد إنهاء اللعبة الحالية والبدء من جديد؟",
      "KEEP_PLAYING": "مواصلة اللعب",
      "ASKS_ARROW": "▼  يسأل  ▼",
      "FUNNY_TAGLINE_1": "تحذير: قد يسبب مشاكل في الثقة",
      "FUNNY_TAGLINE_2": "أصدقاؤك على الأرجح يكذبون",
      "FUNNY_TAGLINE_3": "لا أحد بريء هنا",
      "FUNNY_TAGLINE_4": "الشك مضمون",
      "FUNNY_TAGLINE_5": "اختبار الصداقات منذ 2025",
      "FUNNY_TAGLINE_6": "المتسلل يقرأ هذا الآن",
      "FUNNY_TAGLINE_7": "اتهامات مفبركة 100%",
      "FUNNY_TAGLINE_8": "اتهم أحداً. أي أحد.",
      "FUNNY_TAGLINE_9": "حتى المضيف مشبوه",
      "FUNNY_TAGLINE_10": "أشر بإصبعك. دمّر الصداقات.",
      "FUNNY_TAGLINE_11": "الآثار الجانبية تشمل جنون العظمة والتعرق البارد",
      "FUNNY_TAGLINE_12": "لم تتضرر أي صداقات في هذه اللعبة... ربما",
      "FUNNY_TAGLINE_13": "الراعي الرسمي للصمت المحرج",
      "FUNNY_TAGLINE_14": "التواصل البصري = شك فوري",
      "FUNNY_TAGLINE_15": "الهادئ هو الفاعل. دائماً.",
      "FUNNY_TAGLINE_16": "وجه البوكر مطلوب. النتائج قد تختلف.",
      "FUNNY_TAGLINE_17": "مثبت علمياً لإتلاف سهرات الألعاب",
      "FUNNY_TAGLINE_18": "لا تثق بأحد. ولا حتى نفسك.",
      "FUNNY_TAGLINE_19": "الكذب: المهارة الوحيدة التي تهم هنا",
      "FUNNY_TAGLINE_20": "مفاجأة قادمة. كل. جولة.",
      "FUNNY_TAGLINE_21": "وجهك يكشفك",
      "FUNNY_TAGLINE_22": "المتسلل فاز بالفعل في مسابقة التحديق",
      "FUNNY_TAGLINE_23": "بدعم من مشاكل الثقة في الساعة الرابعة صباحاً",
      "FUNNY_TAGLINE_24": "الاتهام هو مجرد صدق بخطوات إضافية",
      "FUNNY_TAGLINE_25": "قد يحتوي على آثار من الخيانة",
      "FUNNY_TAGLINE_26": "تلاعب بعقول أصدقائك، بمسؤولية",
      "FUNNY_TAGLINE_27": "لا أحد يحب الكاذب السيء. تحسّن.",
      "FUNNY_TAGLINE_28": "تتعرق؟ على الأرجح أنت المتسلل.",
      "FUNNY_TAGLINE_29": "الكذب يكون أحلى مع وجود الأصدقاء",
      "FUNNY_TAGLINE_30": "تحذير: وجه البوكر الخاص بك فظيع",
      "CUSTOM_COMMA_HINT": "افصل بالفواصل · موضوع واحد على الأقل",
      "PASS_AND_PLAY": "تمرير واللعب",
      "LOCAL_MULTIPLAYER": "لعب محلي متعدد",
      "LAN_CONNECT_HINT": "العب معاً على نفس الواي فاي أو نقطة بلوتوث",
      "LAN_HOST_BUTTON": "استضف لعبة",
      "LAN_HOST_DESC": "ابدأ لعبة على هذا الجهاز. يمكن للآخرين الانضمام عبر IP.",
      "LAN_JOIN_BUTTON": "انضم إلى لعبة",
      "LAN_JOIN_DESC": "ابحث تلقائياً أو أدخل عنوان IP للمضيف.",
      "LAN_HOST_TITLE": "استضافة اللعبة",
      "LAN_HOST_IP_LABEL": "عنوان IP الخاص بك:",
      "LAN_HOST_WAITING": "في انتظار انضمام اللاعبين...",
      "LAN_HOST_START_GAME": "ابدأ اللعبة",
      "LAN_HOST_MIN_PLAYERS": "تحتاج ٣ لاعبين على الأقل للبدء",
      "LAN_JOIN_TITLE": "الانضمام إلى لعبة",
      "LAN_JOIN_AUTO_LABEL": "ألعاب موجودة قريباً",
      "LAN_JOIN_SCANNING": "جاري البحث عن الألعاب...",
      "LAN_JOIN_IP_HINT": "أو أدخل IP المضيف يدوياً",
      "LAN_JOIN_CONNECT": "اتصال",
      "LAN_JOIN_CONNECTING": "جاري الاتصال...",
      "LAN_JOIN_WAITING": "متصل! في انتظار المضيف لبدء اللعبة...",
      "LAN_JOIN_FAILED": "فشل الاتصال. تحقق من IP وحاول مرة أخرى.",
      "LAN_AVATAR_TITLE": "اختر شخصيتك",
      "LAN_AVATAR_CONFIRM": "تأكيد",
      "LAN_AVATAR_READY_COUNT": "{ready} / {total} جاهز",
      "LAN_ROLE_REVEAL_TITLE": "دورك",
      "LAN_ROLE_WAITING": "في انتظار جميع اللاعبين...",
      "LAN_QUESTIONS_HOST_HINT": "اضغط التالي للانتقال",
      "LAN_QUESTIONS_CLIENT_HINT": "المضيف يتحكم في الأسئلة",
      "LAN_VOTES_COUNT": "أصوات: {count} / {total}",
      "LAN_REVEAL_CLIENT_WAIT": "في انتظار المضيف للمتابعة...",
      "LAN_GUESS_WAITING": "المتسلل يفكر...",
      "LAN_SUMMARY_CLIENT_WAIT": "في انتظار المضيف...",
      "IMPOSTER_FLED_TITLE": "هرب المتسلل!",
      "IMPOSTER_FLED_MESSAGE": "هرب {name} كالجبان! الجميع يحصل على ١٠٠ نقطة!",
      "HOST_LEFT_MESSAGE": "غادر المضيف اللعبة.",
      "QUIT_CONFIRM_LAN": "تريد مغادرة اللعبة المتعددة؟ سيتأثر اللاعبون الآخرون.",
      "LAN_NAME_LABEL": "اسمك",
      "LAN_BLUETOOTH_TIP": "بلا واي فاي؟ فعّل نقطة البلوتوث على جهاز واحد وأوصل الأجهزة الأخرى به.",
      "CONFIRM_VOTE": "تأكيد التصويت",
      "CANCEL": "إلغاء",
      "YES_FINISH": "نعم، انهِ",
      "KEEP_THIS": "مكافأة السرعة محفوظة",
      "CONFIRM_END_GAME": "هل تريد إنهاء اللعبة؟",
      "ROUND_BONUS": "مكافأة الجولة",
      "BONUS_ALL_PLAYERS": "{delta} نقطة لجميع اللاعبين!",
      "BONUS_FROM_ROUND": "{delta} نقطة بونس",
      "LOADING_IMAGE": "جارٍ تحميل الصورة...",
      "TAP_TO_CLOSE": "اضغط في أي مكان للإغلاق",
      "HOW_STEP6_TITLE": "مكافأة السرعة",
      "HOW_STEP6_DESC": "مجموع ⚡ 500 نقطة يتناقص أثناء النقاش. أنهِ الأسئلة بسرعة للحفاظ على المزيد — تُوزَّع على غير المتسللين!",
      "HOW_STEP8_TITLE": "الدوران المحظوظ",
      "HOW_STEP8_DESC": "قبل كل لوحة نقاط، تدور آلة الحظ للجميع! فوز (60%): +50 للكل. خسارة (40%): −50. النقاط لا تنزل تحت الصفر."
    }
  },
  "ja": {
    "translation": {
      "GAME_TITLE": "インポスター",
      "TAGLINE": "誰が紛れ込んでいる？",
      "LANGUAGE_SELECT": "言語を選択",
      "NEW_GAME": "新しいゲーム",
      "HOW_TO_PLAY": "遊び方",
      "HOW_TITLE": "遊び方",
      "HOW_STEP1_TITLE": "セットアップ",
      "HOW_STEP1_DESC": "3〜8人のプレイヤー名を入力し、カテゴリーを選択します。",
      "HOW_STEP2_TITLE": "役割を確認",
      "HOW_STEP2_DESC": "順番に携帯を回します。一人がインポスターで、お題を知りません！",
      "HOW_STEP3_TITLE": "質問する",
      "HOW_STEP3_DESC": "プレイヤーは交互にお題についてはい/いいえの質問をします。インポスターはごまかします！",
      "HOW_STEP4_TITLE": "投票",
      "HOW_STEP4_DESC": "全員がインポスターだと思う人に密かに投票します。自分には投票できません — ハードモードを除く！",
      "HOW_STEP5_TITLE": "得点",
      "HOW_STEP5_DESC": "インポスター正解 = +100点。インポスターがお題を当てる = +100点。全員を騙す = +200ボーナス（通常モードのみ）。ハードモード：自己投票 = +100点；騙したボーナスなし。",
      "BACK": "戻る",
      "CONTINUE": "続ける",
      "DONE": "了解！",
      "SETUP_TITLE": "ゲーム設定",
      "ADD_PLAYER": "+ プレイヤー追加",
      "REMOVE_PLAYER": "最後を削除",
      "PLAYER_N": "プレイヤー{n}",
      "PLAYER_NAME_HINT": "プレイヤー名...",
      "PLAYERS_LABEL": "プレイヤー ({count}人)",
      "MIN_PLAYERS_WARNING": "3人以上必要です！",
      "EMPTY_NAME_WARNING": "全員の名前を入力してください！",
      "DUPLICATE_NAME_WARNING": "同じ名前のプレイヤーは使用できません！",
      "HARD_MODE": "ハードモード",
      "HARD_MODE_HINT": "インポスターは偽のテーマを見る — 誰も正体を知らない！",
      "SELECT_CATEGORY": "カテゴリーを選ぶ",
      "START_GAME": "ゲームスタート！",
      "PASS_TO": "{name}さんへ渡してください",
      "TAP_TO_REVEAL": "タップして役割を確認",
      "PLAYER_X_OF_Y": "{total}人中{current}人目",
      "PRIVACY_NOTE": "他の人に見せないで！",
      "YOU_ARE_IMPOSTER": "あなたは\nインポスターです！",
      "IMPOSTER_DESCRIPTION": "お題がわかりません。上手く質問して、見破られないようにしてください！",
      "YOU_KNOW_SUBJECT": "お題は：",
      "REMEMBER_SUBJECT": "覚えてください！声に出さないで。",
      "QUESTION_PHASE_TITLE": "質問タイム",
      "QUESTION_COUNT": "質問 {current} / {total}",
      "PLAYER_ASKS": "{asker} が {answerer} に質問",
      "ASK_INSTRUCTIONS": "お題についてはい/いいえで答えられる質問をしてください",
      "NEXT_QUESTION": "次の質問",
      "FINISH_QUESTIONS": "質問終了して投票へ",
      "VOTING_TITLE": "インポスターに投票",
      "VOTING_PLAYER": "{name}さん、インポスターは誰ですか？",
      "VOTING_INSTRUCTIONS": "インポスターは誰？名前をタップして投票！",
      "VOTE_SUBMIT": "投票する",
      "REVEAL_TITLE": "インポスターは…",
      "CORRECT_VOTERS": "正解した人",
      "INCORRECT_VOTERS": "騙された人",
      "NOBODY_GUESSED": "誰もインポスターを見破れなかった！ +200ボーナス！",
      "GUESS_TITLE": "インポスターの最後の挑戦",
      "PASS_TO_IMPOSTER": "{name}（インポスター）に渡してください",
      "GUESS_INSTRUCTIONS": "皆が話していたお題は何でしたか？",
      "SUBMIT_GUESS": "答えを送信",
      "GUESS_CORRECT": "正解！ +100点！",
      "GUESS_WRONG": "不正解！お題は: {subject}",
      "SUMMARY_TITLE": "ラウンド{round}の結果",
      "SCORES_TITLE": "スコアボード",
      "NEXT_ROUND": "次のラウンド",
      "END_GAME": "ゲーム終了",
      "WINNER_IS": "トップ：{name}",
      "CAT_RANDOM": "🎲 ランダム",
      "CAT_FOOD": "🍕 食べ物",
      "CAT_ANIMALS": "🦁 動物",
      "CAT_COUNTRIES": "🌍 国",
      "CAT_SPORTS": "⚽ スポーツ",
      "CAT_VEHICLES": "✈️ 乗り物",
      "CAT_CLOTHING": "👗 衣類",
      "CAT_NATURE": "🌈 自然",
      "CAT_MOVIES": "🎬 映画",
      "CAT_MUSIC": "🎵 音楽",
      "CAT_CUSTOM": "✏️ カスタム",
      "SETTINGS": "設定",
      "MUSIC_ON": "♫ 音楽: ON",
      "MUSIC_OFF": "✕ 音楽: OFF",
      "CUSTOM_SUBJECTS_HINT": "りんご、車、ギター、...",
      "CUSTOM_MIN_WARNING": "1つ以上の項目を入力してください！",
      "LOADING_OPTIONS": "選択肢を検索中…",
      "SAVED_GAME_FOUND": "ゲーム進行中",
      "RESUME_ROUND_INFO": "ラウンド {round} · {players} 人",
      "RESUME_GAME": "▶  再開",
      "START_FRESH": "新しいゲーム",
      "CREDITS": "クレジット",
      "QUIT_GAME": "メニューに戻る",
      "QUIT_CONFIRM": "現在のゲームを終了して最初からやり直しますか？",
      "KEEP_PLAYING": "続ける",
      "ASKS_ARROW": "▼  に聞く  ▼",
      "FUNNY_TAGLINE_1": "警告：信頼問題を引き起こす可能性あり",
      "FUNNY_TAGLINE_2": "友達はたぶん嘘をついている",
      "FUNNY_TAGLINE_3": "ここに無実の人はいない",
      "FUNNY_TAGLINE_4": "疑惑保証済み",
      "FUNNY_TAGLINE_5": "2025年から友情テスト中",
      "FUNNY_TAGLINE_6": "インポスターがこれを読んでいる",
      "FUNNY_TAGLINE_7": "100%でっち上げの告発",
      "FUNNY_TAGLINE_8": "誰かを責めろ。誰でもいい。",
      "FUNNY_TAGLINE_9": "ホストも怪しい",
      "FUNNY_TAGLINE_10": "指を指せ。友情を破壊しろ。",
      "FUNNY_TAGLINE_11": "副作用：妄想症と冷や汗",
      "FUNNY_TAGLINE_12": "このゲームでは友情は傷つきません…たぶん",
      "FUNNY_TAGLINE_13": "気まずい沈黙の公式スポンサー",
      "FUNNY_TAGLINE_14": "目が合う = 即疑惑",
      "FUNNY_TAGLINE_15": "静かな人がやった。いつも。",
      "FUNNY_TAGLINE_16": "ポーカーフェイスが必要。結果は変わるかも。",
      "FUNNY_TAGLINE_17": "ゲームナイトを台無しにすることが科学的に証明されています",
      "FUNNY_TAGLINE_18": "誰も信じるな。自分自身でさえも。",
      "FUNNY_TAGLINE_19": "嘘をつく：ここで重要な唯一のスキル",
      "FUNNY_TAGLINE_20": "どんでん返しが来る。毎。ラウンド。",
      "FUNNY_TAGLINE_21": "あなたの顔がバレてる",
      "FUNNY_TAGLINE_22": "インポスターはすでに睨み合いで勝った",
      "FUNNY_TAGLINE_23": "午前4時の信頼問題スポンサード",
      "FUNNY_TAGLINE_24": "非難は追加のステップを伴う誠実さ",
      "FUNNY_TAGLINE_25": "裏切りの痕跡を含む場合があります",
      "FUNNY_TAGLINE_26": "友達をガスライティング、責任を持って",
      "FUNNY_TAGLINE_27": "下手な嘘つきは誰も好かない。上達しろ。",
      "FUNNY_TAGLINE_28": "汗かいてる？たぶんインポスターだな。",
      "FUNNY_TAGLINE_29": "嘘は友達の前でより美味しい",
      "FUNNY_TAGLINE_30": "警告：あなたのポーカーフェイスはひどい",
      "CUSTOM_COMMA_HINT": "カンマで区切る · 最低1つのテーマ",
      "PASS_AND_PLAY": "パス&プレイ",
      "LOCAL_MULTIPLAYER": "ローカルマルチプレイ",
      "LAN_CONNECT_HINT": "同じWiFiまたはBluetoothホットスポットで一緒にプレイ",
      "LAN_HOST_BUTTON": "ゲームをホスト",
      "LAN_HOST_DESC": "このデバイスでゲームを開始。他の人はIPを入力して参加。",
      "LAN_JOIN_BUTTON": "ゲームに参加",
      "LAN_JOIN_DESC": "近くのゲームを自動検索、またはホストのIPを入力。",
      "LAN_HOST_TITLE": "ゲーム作成中",
      "LAN_HOST_IP_LABEL": "あなたのIPアドレス:",
      "LAN_HOST_WAITING": "参加者を待っています...",
      "LAN_HOST_START_GAME": "ゲーム開始",
      "LAN_HOST_MIN_PLAYERS": "開始するには3人以上必要です",
      "LAN_JOIN_TITLE": "ゲームに参加",
      "LAN_JOIN_AUTO_LABEL": "近くで見つかったゲーム",
      "LAN_JOIN_SCANNING": "ゲームを検索中...",
      "LAN_JOIN_IP_HINT": "またはホストのIPを手動入力",
      "LAN_JOIN_CONNECT": "接続",
      "LAN_JOIN_CONNECTING": "接続中...",
      "LAN_JOIN_WAITING": "接続済み！ホストの開始を待っています...",
      "LAN_JOIN_FAILED": "接続に失敗しました。IPを確認して再試行してください。",
      "LAN_AVATAR_TITLE": "アバターを選択",
      "LAN_AVATAR_CONFIRM": "確定",
      "LAN_AVATAR_READY_COUNT": "{ready} / {total} 準備完了",
      "LAN_ROLE_REVEAL_TITLE": "あなたの役割",
      "LAN_ROLE_WAITING": "全員を待っています...",
      "LAN_QUESTIONS_HOST_HINT": "次へをタップして進める",
      "LAN_QUESTIONS_CLIENT_HINT": "ホストが質問をコントロール中",
      "LAN_VOTES_COUNT": "投票数: {count} / {total}",
      "LAN_REVEAL_CLIENT_WAIT": "ホストの続行を待っています...",
      "LAN_GUESS_WAITING": "インポスターが考えています...",
      "LAN_SUMMARY_CLIENT_WAIT": "ホストを待っています...",
      "IMPOSTER_FLED_TITLE": "インポスターが逃げた！",
      "IMPOSTER_FLED_MESSAGE": "{name}はチキンのように逃げた！みんな100ポイント獲得！",
      "HOST_LEFT_MESSAGE": "ホストがゲームを離れました。",
      "QUIT_CONFIRM_LAN": "マルチプレイゲームを終了しますか？他のプレイヤーに影響します。",
      "LAN_NAME_LABEL": "あなたの名前",
      "LAN_BLUETOOTH_TIP": "WiFiなし？1台でBluetoothホットスポットを有効にして他を接続。",
      "CONFIRM_VOTE": "投票を確認",
      "CANCEL": "キャンセル",
      "YES_FINISH": "はい、終了",
      "KEEP_THIS": "スピードボーナス保存",
      "CONFIRM_END_GAME": "ゲームを終了しますか？",
      "ROUND_BONUS": "ラウンドボーナス",
      "BONUS_ALL_PLAYERS": "全員に{delta}ポイント！",
      "BONUS_FROM_ROUND": "ボーナス{delta}pts",
      "LOADING_IMAGE": "画像を読込中...",
      "TAP_TO_CLOSE": "どこかタップして閉じる",
      "HOW_STEP6_TITLE": "スピードボーナス",
      "HOW_STEP6_DESC": "議論中に⚡500ptが減っていく。早く終わるほど非インポスターが多くもらえる！",
      "HOW_STEP8_TITLE": "ラッキースピン",
      "HOW_STEP8_DESC": "毎スコアボード前に全員のスロットが回る！勝ち(60%): 全員+50pt。負け(40%): 全員−50pt。スコアは0以下にならない。"
    }
  },
  "zh": {
    "translation": {
      "GAME_TITLE": "卧底",
      "TAGLINE": "谁是卧底？",
      "LANGUAGE_SELECT": "选择语言",
      "NEW_GAME": "新游戏",
      "HOW_TO_PLAY": "如何游玩",
      "HOW_TITLE": "如何游玩",
      "HOW_STEP1_TITLE": "设置",
      "HOW_STEP1_DESC": "输入3-8名玩家姓名并选择类别。",
      "HOW_STEP2_TITLE": "查看角色",
      "HOW_STEP2_DESC": "把手机传给每个玩家。一名玩家是卧底，他不知道主题！",
      "HOW_STEP3_TITLE": "提问",
      "HOW_STEP3_DESC": "玩家轮流向彼此提出关于主题的是/否问题。卧底要蒙混过关！",
      "HOW_STEP4_TITLE": "投票",
      "HOW_STEP4_DESC": "所有人秘密投票选出他们认为的卧底。不能投票给自己——困难模式除外！",
      "HOW_STEP5_TITLE": "计分",
      "HOW_STEP5_DESC": "正确猜出卧底 = +100分。卧底猜出主题 = +100分。卧底骗过所有人 = +200奖励（仅普通模式）。困难模式：自投 = +100分；无骗过全员奖励。",
      "BACK": "返回",
      "CONTINUE": "继续",
      "DONE": "明白了！",
      "SETUP_TITLE": "游戏设置",
      "ADD_PLAYER": "+ 添加玩家",
      "REMOVE_PLAYER": "删除最后一个",
      "PLAYER_N": "玩家{n}",
      "PLAYER_NAME_HINT": "玩家姓名...",
      "PLAYERS_LABEL": "玩家 ({count}人)",
      "MIN_PLAYERS_WARNING": "至少需要3名玩家！",
      "EMPTY_NAME_WARNING": "请填写所有玩家姓名！",
      "DUPLICATE_NAME_WARNING": "不能有两名玩家使用相同名字！",
      "HARD_MODE": "困难模式",
      "HARD_MODE_HINT": "冒充者看到假题目——没人知道他是谁！",
      "SELECT_CATEGORY": "选择类别",
      "START_GAME": "开始游戏！",
      "PASS_TO": "请传给 {name}",
      "TAP_TO_REVEAL": "点击查看你的角色",
      "PLAYER_X_OF_Y": "第{current}位 / 共{total}位",
      "PRIVACY_NOTE": "不要给其他人看！",
      "YOU_ARE_IMPOSTER": "你是\n卧底！",
      "IMPOSTER_DESCRIPTION": "你不知道主题。聪明地提问，不要被发现！",
      "YOU_KNOW_SUBJECT": "主题是：",
      "REMEMBER_SUBJECT": "记住它！不要说出声。",
      "QUESTION_PHASE_TITLE": "提问时间",
      "QUESTION_COUNT": "问题 {current} / {total}",
      "PLAYER_ASKS": "{asker} 问 {answerer}",
      "ASK_INSTRUCTIONS": "提出一个关于主题的是/否问题",
      "NEXT_QUESTION": "下一个问题",
      "FINISH_QUESTIONS": "结束提问并投票",
      "VOTING_TITLE": "投票选出卧底",
      "VOTING_PLAYER": "{name}，谁是卧底？",
      "VOTING_INSTRUCTIONS": "谁是卧底？点击名字投票！",
      "VOTE_SUBMIT": "提交投票",
      "REVEAL_TITLE": "卧底是…",
      "CORRECT_VOTERS": "猜对的人",
      "INCORRECT_VOTERS": "被骗的人",
      "NOBODY_GUESSED": "没人抓到卧底！+200奖励！",
      "GUESS_TITLE": "卧底最后的机会",
      "PASS_TO_IMPOSTER": "请传给 {name}（卧底）",
      "GUESS_INSTRUCTIONS": "大家讨论的主题是什么？",
      "SUBMIT_GUESS": "提交猜测",
      "GUESS_CORRECT": "正确！+100分！",
      "GUESS_WRONG": "错了！主题是：{subject}",
      "SUMMARY_TITLE": "第{round}轮总结",
      "SCORES_TITLE": "积分榜",
      "NEXT_ROUND": "下一轮",
      "END_GAME": "结束游戏",
      "WINNER_IS": "领先：{name}",
      "CAT_RANDOM": "🎲 随机",
      "CAT_FOOD": "🍕 食物",
      "CAT_ANIMALS": "🦁 动物",
      "CAT_COUNTRIES": "🌍 国家",
      "CAT_SPORTS": "⚽ 运动",
      "CAT_VEHICLES": "✈️ 交通工具",
      "CAT_CLOTHING": "👗 服装",
      "CAT_NATURE": "🌈 自然",
      "CAT_MOVIES": "🎬 电影",
      "CAT_MUSIC": "🎵 音乐",
      "CAT_CUSTOM": "✏️ 自定义",
      "SETTINGS": "设置",
      "MUSIC_ON": "♫ 音乐: 开",
      "MUSIC_OFF": "✕ 音乐: 关",
      "CUSTOM_SUBJECTS_HINT": "苹果、汽车、吉他、...",
      "CUSTOM_MIN_WARNING": "请输入至少1个主题！",
      "LOADING_OPTIONS": "正在查找选项…",
      "SAVED_GAME_FOUND": "游戏进行中",
      "RESUME_ROUND_INFO": "第 {round} 轮 · {players} 位玩家",
      "RESUME_GAME": "▶  继续",
      "START_FRESH": "新游戏",
      "CREDITS": "制作人员",
      "QUIT_GAME": "退出到菜单",
      "QUIT_CONFIRM": "结束当前游戏并重新开始？",
      "KEEP_PLAYING": "继续游戏",
      "ASKS_ARROW": "▼  问  ▼",
      "FUNNY_TAGLINE_1": "警告：可能导致信任危机",
      "FUNNY_TAGLINE_2": "你的朋友可能在撒谎",
      "FUNNY_TAGLINE_3": "这里没有无辜的人",
      "FUNNY_TAGLINE_4": "疑惑保证",
      "FUNNY_TAGLINE_5": "2025年起测试友谊",
      "FUNNY_TAGLINE_6": "冒充者正在读这个",
      "FUNNY_TAGLINE_7": "100%捏造的指控",
      "FUNNY_TAGLINE_8": "指责某人。任何人。",
      "FUNNY_TAGLINE_9": "就连主持人也很可疑",
      "FUNNY_TAGLINE_10": "指手画脚。毁掉友谊。",
      "FUNNY_TAGLINE_11": "副作用包括偏执和冷汗",
      "FUNNY_TAGLINE_12": "这个游戏中没有友谊受到伤害……也许",
      "FUNNY_TAGLINE_13": "尴尬沉默的官方赞助商",
      "FUNNY_TAGLINE_14": "眼神接触 = 立即怀疑",
      "FUNNY_TAGLINE_15": "那个安静的人干的。一直都是。",
      "FUNNY_TAGLINE_16": "需要扑克脸。结果可能不同。",
      "FUNNY_TAGLINE_17": "科学证明可以毁掉游戏之夜",
      "FUNNY_TAGLINE_18": "不要相信任何人。甚至不要相信自己。",
      "FUNNY_TAGLINE_19": "撒谎：这里唯一重要的技能",
      "FUNNY_TAGLINE_20": "情节转折来了。每一轮。",
      "FUNNY_TAGLINE_21": "你的表情出卖了你",
      "FUNNY_TAGLINE_22": "冒充者已经赢得了瞪视比赛",
      "FUNNY_TAGLINE_23": "由凌晨4点的信任危机赞助",
      "FUNNY_TAGLINE_24": "指控不过是多了几步的诚实",
      "FUNNY_TAGLINE_25": "可能含有背叛痕迹",
      "FUNNY_TAGLINE_26": "负责任地对朋友进行心理操控",
      "FUNNY_TAGLINE_27": "没人喜欢差劲的骗子。提高吧。",
      "FUNNY_TAGLINE_28": "在出汗？可能是冒充者。",
      "FUNNY_TAGLINE_29": "有朋友在身边，谎言更有滋味",
      "FUNNY_TAGLINE_30": "警告：你的扑克脸很糟糕",
      "CUSTOM_COMMA_HINT": "用逗号分隔 · 至少1个主题",
      "PASS_AND_PLAY": "传递游玩",
      "LOCAL_MULTIPLAYER": "本地多人",
      "LAN_CONNECT_HINT": "通过同一WiFi或蓝牙热点一起玩",
      "LAN_HOST_BUTTON": "创建游戏",
      "LAN_HOST_DESC": "在此设备上开始游戏。其他人可以通过IP加入。",
      "LAN_JOIN_BUTTON": "加入游戏",
      "LAN_JOIN_DESC": "自动查找附近游戏，或输入主机IP地址。",
      "LAN_HOST_TITLE": "创建游戏中",
      "LAN_HOST_IP_LABEL": "你的IP地址:",
      "LAN_HOST_WAITING": "等待玩家加入...",
      "LAN_HOST_START_GAME": "开始游戏",
      "LAN_HOST_MIN_PLAYERS": "至少需要3名玩家才能开始",
      "LAN_JOIN_TITLE": "加入游戏",
      "LAN_JOIN_AUTO_LABEL": "附近的游戏",
      "LAN_JOIN_SCANNING": "正在搜索游戏...",
      "LAN_JOIN_IP_HINT": "或手动输入主机IP",
      "LAN_JOIN_CONNECT": "连接",
      "LAN_JOIN_CONNECTING": "连接中...",
      "LAN_JOIN_WAITING": "已连接！等待主机开始...",
      "LAN_JOIN_FAILED": "连接失败。请检查IP并重试。",
      "LAN_AVATAR_TITLE": "选择你的头像",
      "LAN_AVATAR_CONFIRM": "确认",
      "LAN_AVATAR_READY_COUNT": "{ready} / {total} 准备好了",
      "LAN_ROLE_REVEAL_TITLE": "你的角色",
      "LAN_ROLE_WAITING": "等待所有玩家...",
      "LAN_QUESTIONS_HOST_HINT": "点击下一步继续",
      "LAN_QUESTIONS_CLIENT_HINT": "主机控制问题",
      "LAN_VOTES_COUNT": "投票: {count} / {total}",
      "LAN_REVEAL_CLIENT_WAIT": "等待主机继续...",
      "LAN_GUESS_WAITING": "骗子在思考...",
      "LAN_SUMMARY_CLIENT_WAIT": "等待主机...",
      "IMPOSTER_FLED_TITLE": "骗子跑了！",
      "IMPOSTER_FLED_MESSAGE": "{name}像懦夫一样逃跑了！大家各得100分！",
      "HOST_LEFT_MESSAGE": "主机已离开游戏。",
      "QUIT_CONFIRM_LAN": "退出多人游戏？其他玩家将受影响。",
      "LAN_NAME_LABEL": "你的名字",
      "LAN_BLUETOOTH_TIP": "没有WiFi？在一台设备上开启蓝牙热点并连接其他设备。",
      "CONFIRM_VOTE": "确认投票",
      "CANCEL": "取消",
      "YES_FINISH": "是的，结束",
      "KEEP_THIS": "速度奖励已保存",
      "CONFIRM_END_GAME": "结束游戏？",
      "ROUND_BONUS": "回合奖励",
      "BONUS_ALL_PLAYERS": "所有玩家{delta}分！",
      "BONUS_FROM_ROUND": "奖励{delta}分",
      "LOADING_IMAGE": "加载图片中...",
      "TAP_TO_CLOSE": "点击任意处关闭",
      "HOW_STEP6_TITLE": "速度奖励",
      "HOW_STEP6_DESC": "讨论期间⚡500分持续减少。越快结束问题环节，非卧底获得的奖励越多！",
      "HOW_STEP8_TITLE": "幸运转盘",
      "HOW_STEP8_DESC": "每次积分板前转动老虎机！赢（60%）：全员+50分。输（40%）：全员−50分。最低分始终为0。"
    }
  },
  "ko": {
    "translation": {
      "GAME_TITLE": "임포스터",
      "TAGLINE": "누가 임포스터인가?",
      "LANGUAGE_SELECT": "언어 선택",
      "NEW_GAME": "새 게임",
      "HOW_TO_PLAY": "게임 방법",
      "HOW_TITLE": "게임 방법",
      "HOW_STEP1_TITLE": "설정",
      "HOW_STEP1_DESC": "3-8명의 이름을 입력하고 카테고리를 선택하세요.",
      "HOW_STEP2_TITLE": "역할 확인",
      "HOW_STEP2_DESC": "차례로 폰을 건네세요. 임포스터는 주제를 모릅니다!",
      "HOW_STEP3_TITLE": "질문하기",
      "HOW_STEP3_DESC": "플레이어들이 주제에 대해 예/아니오 질문을 합니다. 임포스터는 블러핑!",
      "HOW_STEP4_TITLE": "투표",
      "HOW_STEP4_DESC": "모두 임포스터라고 생각하는 사람에게 비밀 투표를 합니다. 자신에게는 투표할 수 없습니다 — 하드 모드 제외!",
      "HOW_STEP5_TITLE": "점수",
      "HOW_STEP5_DESC": "임포스터 정확히 맞춤 = +100점. 임포스터 주제 맞춤 = +100점. 모두 속임 = +200 보너스(일반 모드 전용). 하드 모드: 자기 투표 = +100점; 속임 보너스 없음.",
      "BACK": "뒤로",
      "CONTINUE": "계속",
      "DONE": "알겠어요!",
      "SETUP_TITLE": "게임 설정",
      "ADD_PLAYER": "+ 플레이어 추가",
      "REMOVE_PLAYER": "마지막 제거",
      "PLAYER_N": "플레이어 {n}",
      "PLAYER_NAME_HINT": "플레이어 이름...",
      "PLAYERS_LABEL": "플레이어 ({count}명)",
      "MIN_PLAYERS_WARNING": "최소 3명 필요합니다!",
      "EMPTY_NAME_WARNING": "모든 플레이어의 이름을 입력하세요!",
      "DUPLICATE_NAME_WARNING": "두 플레이어가 같은 이름을 쓸 수 없습니다!",
      "HARD_MODE": "하드 모드",
      "HARD_MODE_HINT": "임포스터는 가짜 주제를 봐요 — 아무도 누군지 몰라요!",
      "SELECT_CATEGORY": "카테고리 선택",
      "START_GAME": "게임 시작!",
      "PASS_TO": "{name}에게 전달하세요",
      "TAP_TO_REVEAL": "탭하여 역할 확인",
      "PLAYER_X_OF_Y": "{total}명 중 {current}번째",
      "PRIVACY_NOTE": "다른 사람에게 보이지 마세요!",
      "YOU_ARE_IMPOSTER": "당신이\n임포스터입니다!",
      "IMPOSTER_DESCRIPTION": "주제를 모릅니다. 영리하게 질문하고 들키지 마세요!",
      "YOU_KNOW_SUBJECT": "주제는:",
      "REMEMBER_SUBJECT": "기억하세요! 소리 내어 말하지 마세요.",
      "QUESTION_PHASE_TITLE": "질문 시간",
      "QUESTION_COUNT": "질문 {current} / {total}",
      "PLAYER_ASKS": "{asker}가 {answerer}에게 질문",
      "ASK_INSTRUCTIONS": "주제에 대해 예/아니오로 답할 수 있는 질문을 하세요",
      "NEXT_QUESTION": "다음 질문",
      "FINISH_QUESTIONS": "질문 종료 및 투표",
      "VOTING_TITLE": "임포스터에게 투표",
      "VOTING_PLAYER": "{name}, 임포스터는 누구인가요?",
      "VOTING_INSTRUCTIONS": "임포스터는 누구? 이름을 탭하여 투票!",
      "VOTE_SUBMIT": "투표하기",
      "REVEAL_TITLE": "임포스터는…",
      "CORRECT_VOTERS": "정확히 맞춘 사람",
      "INCORRECT_VOTERS": "임포스터에게 속은 사람",
      "NOBODY_GUESSED": "아무도 임포스터를 찾지 못했습니다! +200 보너스!",
      "GUESS_TITLE": "임포스터의 마지막 기회",
      "PASS_TO_IMPOSTER": "{name}(임포스터)에게 전달하세요",
      "GUESS_INSTRUCTIONS": "모두가 이야기하던 주제는 무엇인가요?",
      "SUBMIT_GUESS": "추측 제출",
      "GUESS_CORRECT": "정답! +100점!",
      "GUESS_WRONG": "틀렸습니다! 주제는: {subject}",
      "SUMMARY_TITLE": "라운드 {round} 요약",
      "SCORES_TITLE": "점수판",
      "NEXT_ROUND": "다음 라운드",
      "END_GAME": "게임 종료",
      "WINNER_IS": "선두: {name}",
      "CAT_RANDOM": "🎲 랜덤",
      "CAT_FOOD": "🍕 음식",
      "CAT_ANIMALS": "🦁 동물",
      "CAT_COUNTRIES": "🌍 나라",
      "CAT_SPORTS": "⚽ 스포츠",
      "CAT_VEHICLES": "✈️ 탈것",
      "CAT_CLOTHING": "👗 의류",
      "CAT_NATURE": "🌈 자연",
      "CAT_MOVIES": "🎬 영화",
      "CAT_MUSIC": "🎵 음악",
      "CAT_CUSTOM": "✏️ 커스텀",
      "SETTINGS": "설정",
      "MUSIC_ON": "♫ 음악: 켜짐",
      "MUSIC_OFF": "✕ 음악: 꺼짐",
      "CUSTOM_SUBJECTS_HINT": "사과, 자동차, 기타, ...",
      "CUSTOM_MIN_WARNING": "최소 1개의 주제를 입력하세요!",
      "LOADING_OPTIONS": "옵션 검색 중…",
      "SAVED_GAME_FOUND": "게임 진행 중",
      "RESUME_ROUND_INFO": "라운드 {round} · {players}명",
      "RESUME_GAME": "▶  계속하기",
      "START_FRESH": "새 게임",
      "CREDITS": "크레딧",
      "QUIT_GAME": "메뉴로 나가기",
      "QUIT_CONFIRM": "현재 게임을 종료하고 처음부터 시작할까요?",
      "KEEP_PLAYING": "계속하기",
      "ASKS_ARROW": "▼  에게 질문  ▼",
      "FUNNY_TAGLINE_1": "경고: 신뢰 문제를 일으킬 수 있음",
      "FUNNY_TAGLINE_2": "친구들은 아마 거짓말하고 있어",
      "FUNNY_TAGLINE_3": "여기엔 무고한 사람이 없어",
      "FUNNY_TAGLINE_4": "의심 보장",
      "FUNNY_TAGLINE_5": "2025년부터 우정 테스트",
      "FUNNY_TAGLINE_6": "임포스터가 이걸 읽고 있어",
      "FUNNY_TAGLINE_7": "100% 날조된 혐의",
      "FUNNY_TAGLINE_8": "누군가를 탓해. 누구든.",
      "FUNNY_TAGLINE_9": "진행자도 수상해",
      "FUNNY_TAGLINE_10": "손가락질해. 우정을 파괴해.",
      "FUNNY_TAGLINE_11": "부작용: 편집증과 식은땀",
      "FUNNY_TAGLINE_12": "이 게임에서 우정은 다치지 않았습니다... 아마도",
      "FUNNY_TAGLINE_13": "어색한 침묵의 공식 스폰서",
      "FUNNY_TAGLINE_14": "눈 마주침 = 즉각적인 의심",
      "FUNNY_TAGLINE_15": "조용한 사람이 했어. 항상.",
      "FUNNY_TAGLINE_16": "포커 페이스 필요. 결과는 다를 수 있음.",
      "FUNNY_TAGLINE_17": "게임의 밤을 망치는 것이 과학적으로 증명됨",
      "FUNNY_TAGLINE_18": "아무도 믿지 마. 자기 자신도.",
      "FUNNY_TAGLINE_19": "거짓말: 여기서 중요한 유일한 기술",
      "FUNNY_TAGLINE_20": "반전이 온다. 매. 라운드.",
      "FUNNY_TAGLINE_21": "당신 얼굴이 다 말해주고 있어",
      "FUNNY_TAGLINE_22": "임포스터는 이미 눈싸움에서 이겼어",
      "FUNNY_TAGLINE_23": "새벽 4시 신뢰 문제 후원",
      "FUNNY_TAGLINE_24": "비난은 그냥 추가 단계가 있는 정직함이야",
      "FUNNY_TAGLINE_25": "배신의 흔적이 포함될 수 있습니다",
      "FUNNY_TAGLINE_26": "친구를 가스라이팅하세요, 책임감 있게",
      "FUNNY_TAGLINE_27": "서툰 거짓말쟁이는 아무도 좋아하지 않아. 나아져.",
      "FUNNY_TAGLINE_28": "땀 흘리고 있어? 아마 임포스터야.",
      "FUNNY_TAGLINE_29": "친구들이 있을 때 거짓말이 더 달콤해",
      "FUNNY_TAGLINE_30": "경고: 당신의 포커 페이스는 최악이야",
      "CUSTOM_COMMA_HINT": "쉼표로 구분 · 최소 1개의 주제",
      "PASS_AND_PLAY": "패스 앤 플레이",
      "LOCAL_MULTIPLAYER": "로컬 멀티플레이",
      "LAN_CONNECT_HINT": "같은 WiFi 또는 블루투스 핫스팟에서 함께 플레이",
      "LAN_HOST_BUTTON": "게임 호스트",
      "LAN_HOST_DESC": "이 기기에서 게임 시작. 다른 플레이어는 IP로 참가.",
      "LAN_JOIN_BUTTON": "게임 참가",
      "LAN_JOIN_DESC": "근처 게임을 자동으로 찾거나 호스트 IP를 입력하세요.",
      "LAN_HOST_TITLE": "게임 호스팅 중",
      "LAN_HOST_IP_LABEL": "내 IP 주소:",
      "LAN_HOST_WAITING": "플레이어를 기다리는 중...",
      "LAN_HOST_START_GAME": "게임 시작",
      "LAN_HOST_MIN_PLAYERS": "시작하려면 최소 3명의 플레이어가 필요합니다",
      "LAN_JOIN_TITLE": "게임 참가",
      "LAN_JOIN_AUTO_LABEL": "근처의 게임",
      "LAN_JOIN_SCANNING": "게임 검색 중...",
      "LAN_JOIN_IP_HINT": "또는 호스트 IP를 직접 입력",
      "LAN_JOIN_CONNECT": "연결",
      "LAN_JOIN_CONNECTING": "연결 중...",
      "LAN_JOIN_WAITING": "연결됨! 호스트가 시작하기를 기다리는 중...",
      "LAN_JOIN_FAILED": "연결 실패. IP를 확인하고 다시 시도하세요.",
      "LAN_AVATAR_TITLE": "아바타 선택",
      "LAN_AVATAR_CONFIRM": "확인",
      "LAN_AVATAR_READY_COUNT": "{ready} / {total} 준비됨",
      "LAN_ROLE_REVEAL_TITLE": "당신의 역할",
      "LAN_ROLE_WAITING": "모든 플레이어를 기다리는 중...",
      "LAN_QUESTIONS_HOST_HINT": "다음을 탭하여 진행",
      "LAN_QUESTIONS_CLIENT_HINT": "호스트가 질문을 제어합니다",
      "LAN_VOTES_COUNT": "투표: {count} / {total}",
      "LAN_REVEAL_CLIENT_WAIT": "호스트가 계속하기를 기다리는 중...",
      "LAN_GUESS_WAITING": "임포스터가 생각 중...",
      "LAN_SUMMARY_CLIENT_WAIT": "호스트를 기다리는 중...",
      "IMPOSTER_FLED_TITLE": "임포스터가 도망쳤어요!",
      "IMPOSTER_FLED_MESSAGE": "{name}가 겁쟁이처럼 도망쳤어요! 모두 100점!",
      "HOST_LEFT_MESSAGE": "호스트가 게임을 떠났습니다.",
      "QUIT_CONFIRM_LAN": "멀티플레이어 게임을 나가시겠습니까? 다른 플레이어에게 영향을 줍니다.",
      "LAN_NAME_LABEL": "이름",
      "LAN_BLUETOOTH_TIP": "WiFi 없음? 한 기기에서 블루투스 핫스팟을 켜고 다른 기기를 연결하세요.",
      "CONFIRM_VOTE": "투표 확인",
      "CANCEL": "취소",
      "YES_FINISH": "네, 끝내기",
      "KEEP_THIS": "스피드 보너스 저장",
      "CONFIRM_END_GAME": "게임을 끝낼까요?",
      "ROUND_BONUS": "라운드 보너스",
      "BONUS_ALL_PLAYERS": "전원 {delta}점!",
      "BONUS_FROM_ROUND": "보너스 {delta}점",
      "LOADING_IMAGE": "이미지 불러오는 중...",
      "TAP_TO_CLOSE": "아무 곳이나 탭하여 닫기",
      "HOW_STEP6_TITLE": "스피드 보너스",
      "HOW_STEP6_DESC": "토론하는 동안 ⚡500점 풀이 줄어든다. 빨리 끝낼수록 비임포스터들이 더 많은 보너스를 받는다!",
      "HOW_STEP8_TITLE": "럭키 스핀",
      "HOW_STEP8_DESC": "매 점수판 전 슬롯 머신이 돈다! 이기면(60%): 전원 +50점. 지면(40%): 전원 −50점. 최저 점수는 0."
    }
  },
  "de": {
    "translation": {
      "GAME_TITLE": "Der Verräter",
      "TAGLINE": "Wer steckt dahinter?",
      "LANGUAGE_SELECT": "Sprache wählen",
      "NEW_GAME": "Neues Spiel",
      "HOW_TO_PLAY": "Spielanleitung",
      "HOW_TITLE": "Spielanleitung",
      "HOW_STEP1_TITLE": "Einrichtung",
      "HOW_STEP1_DESC": "Gib 3-8 Spielernamen ein und wähle eine Kategorie.",
      "HOW_STEP2_TITLE": "Rollen enthüllen",
      "HOW_STEP2_DESC": "Gib das Handy reihum. Einer ist der Verräter – er sieht das Thema nicht!",
      "HOW_STEP3_TITLE": "Fragen stellen",
      "HOW_STEP3_DESC": "Alle fragen sich gegenseitig Ja/Nein-Fragen zum Thema. Der Verräter blufft!",
      "HOW_STEP4_TITLE": "Abstimmung",
      "HOW_STEP4_DESC": "Alle stimmen heimlich ab, wer der Verräter ist. Du kannst nicht für dich selbst stimmen — außer im schwierigen Modus!",
      "HOW_STEP5_TITLE": "Punkte",
      "HOW_STEP5_DESC": "Verräter erraten = +100P. Verräter errät Thema = +100P. Verräter täuscht alle = +200 Bonus (nur normaler Modus). Schwieriger Modus: Selbststimme = +100P; kein Täuschungsbonus.",
      "BACK": "Zurück",
      "CONTINUE": "Weiter",
      "DONE": "Verstanden!",
      "SETUP_TITLE": "Spielvorbereitung",
      "ADD_PLAYER": "+ Spieler hinzufügen",
      "REMOVE_PLAYER": "Letzten löschen",
      "PLAYER_N": "Spieler {n}",
      "PLAYER_NAME_HINT": "Spielername...",
      "PLAYERS_LABEL": "Spieler ({count})",
      "MIN_PLAYERS_WARNING": "Mindestens 3 Spieler benötigt!",
      "EMPTY_NAME_WARNING": "Alle Spielernamen müssen ausgefüllt werden!",
      "DUPLICATE_NAME_WARNING": "Zwei Spieler können nicht denselben Namen haben!",
      "HARD_MODE": "Schwieriger Modus",
      "HARD_MODE_HINT": "Der Verräter sieht ein falsches Thema — niemand kennt seine Identität!",
      "SELECT_CATEGORY": "Kategorie wählen",
      "START_GAME": "Spiel starten!",
      "PASS_TO": "Weiterreichen an {name}",
      "TAP_TO_REVEAL": "Tippen, um Rolle anzuzeigen",
      "PLAYER_X_OF_Y": "Spieler {current} von {total}",
      "PRIVACY_NOTE": "Nicht anderen zeigen!",
      "YOU_ARE_IMPOSTER": "Du bist\nder VERRÄTER!",
      "IMPOSTER_DESCRIPTION": "Du kennst das Thema nicht. Stelle kluge Fragen und lass dich nicht erwischen!",
      "YOU_KNOW_SUBJECT": "Das Thema ist:",
      "REMEMBER_SUBJECT": "Merke es dir! Sag es nicht laut.",
      "QUESTION_PHASE_TITLE": "Fragerunde",
      "QUESTION_COUNT": "Frage {current} von {total}",
      "PLAYER_ASKS": "{asker} fragt {answerer}",
      "ASK_INSTRUCTIONS": "Stelle eine Ja/Nein-Frage zum Thema",
      "NEXT_QUESTION": "Nächste Frage",
      "FINISH_QUESTIONS": "Fragen beenden & Abstimmen",
      "VOTING_TITLE": "Stimme für den Verräter",
      "VOTING_PLAYER": "{name}, wer ist der Verräter?",
      "VOTING_INSTRUCTIONS": "Wer ist der Verräter? Tippe den Namen zum Abstimmen!",
      "VOTE_SUBMIT": "Abstimmen",
      "REVEAL_TITLE": "Der Verräter ist…",
      "CORRECT_VOTERS": "Korrekt identifiziert",
      "INCORRECT_VOTERS": "Vom Verräter getäuscht",
      "NOBODY_GUESSED": "Niemand hat den Verräter erwischt! +200 Bonus!",
      "GUESS_TITLE": "Letzte Chance des Verräters",
      "PASS_TO_IMPOSTER": "Weiterreichen an {name} (den Verräter)",
      "GUESS_INSTRUCTIONS": "Was war das Thema, über das alle geredet haben?",
      "SUBMIT_GUESS": "Antwort abschicken",
      "GUESS_CORRECT": "Richtig! +100 Punkte!",
      "GUESS_WRONG": "Falsch! Das Thema war: {subject}",
      "SUMMARY_TITLE": "Runde {round} – Zusammenfassung",
      "SCORES_TITLE": "Rangliste",
      "NEXT_ROUND": "Nächste Runde",
      "END_GAME": "Spiel beenden",
      "WINNER_IS": "Führend: {name}",
      "CAT_RANDOM": "🎲 Zufällig",
      "CAT_FOOD": "🍕 Essen",
      "CAT_ANIMALS": "🦁 Tiere",
      "CAT_COUNTRIES": "🌍 Länder",
      "CAT_SPORTS": "⚽ Sport",
      "CAT_VEHICLES": "✈️ Fahrzeuge",
      "CAT_CLOTHING": "👗 Kleidung",
      "CAT_NATURE": "🌈 Natur",
      "CAT_MOVIES": "🎬 Filme",
      "CAT_MUSIC": "🎵 Musik",
      "CAT_CUSTOM": "✏️ Eigene",
      "SETTINGS": "Einstellungen",
      "MUSIC_ON": "♫ Musik: AN",
      "MUSIC_OFF": "✕ Musik: AUS",
      "CUSTOM_SUBJECTS_HINT": "Apfel, Auto, Gitarre, ...",
      "CUSTOM_MIN_WARNING": "Gib mindestens 1 Begriff ein!",
      "LOADING_OPTIONS": "Optionen werden geladen…",
      "SAVED_GAME_FOUND": "Spiel läuft noch",
      "RESUME_ROUND_INFO": "Runde {round} · {players} Spieler",
      "RESUME_GAME": "▶  Fortsetzen",
      "START_FRESH": "Neues Spiel",
      "CREDITS": "Credits",
      "QUIT_GAME": "Zum Menü",
      "QUIT_CONFIRM": "Das laufende Spiel beenden und neu starten?",
      "KEEP_PLAYING": "Weiterspielen",
      "ASKS_ARROW": "▼  fragt  ▼",
      "FUNNY_TAGLINE_1": "Warnung: kann Vertrauensprobleme verursachen",
      "FUNNY_TAGLINE_2": "Deine Freunde lügen wahrscheinlich",
      "FUNNY_TAGLINE_3": "Hier ist niemand unschuldig",
      "FUNNY_TAGLINE_4": "Verdacht garantiert",
      "FUNNY_TAGLINE_5": "Freundschaften werden seit 2025 getestet",
      "FUNNY_TAGLINE_6": "Der Verräter liest das gerade",
      "FUNNY_TAGLINE_7": "100% erfundene Anschuldigungen",
      "FUNNY_TAGLINE_8": "Beschuldige jemanden. Irgendjemanden.",
      "FUNNY_TAGLINE_9": "Sogar der Gastgeber ist verdächtig",
      "FUNNY_TAGLINE_10": "Zeig mit dem Finger. Zerstöre Freundschaften.",
      "FUNNY_TAGLINE_11": "Nebenwirkungen: Paranoia und Schweißausbrüche",
      "FUNNY_TAGLINE_12": "Bei diesem Spiel wurde keine Freundschaft verletzt... vielleicht",
      "FUNNY_TAGLINE_13": "Offizieller Sponsor peinlicher Stille",
      "FUNNY_TAGLINE_14": "Augenkontakt = sofortiger Verdacht",
      "FUNNY_TAGLINE_15": "Der Ruhige war's. Immer.",
      "FUNNY_TAGLINE_16": "Pokerface erforderlich. Ergebnisse können variieren.",
      "FUNNY_TAGLINE_17": "Wissenschaftlich bewiesen: ruiniert Spieleabende",
      "FUNNY_TAGLINE_18": "Vertrau niemandem. Nicht mal dir selbst.",
      "FUNNY_TAGLINE_19": "Lügen: die einzige Fähigkeit, die hier zählt",
      "FUNNY_TAGLINE_20": "Plottwist kommt. Jede. Einzelne. Runde.",
      "FUNNY_TAGLINE_21": "Dein Gesicht verrät dich",
      "FUNNY_TAGLINE_22": "Der Verräter hat das Blickduell bereits gewonnen",
      "FUNNY_TAGLINE_23": "Gesponsert von 4-Uhr-morgens-Vertrauensproblemen",
      "FUNNY_TAGLINE_24": "Anschuldigung ist nur Ehrlichkeit mit extra Schritten",
      "FUNNY_TAGLINE_25": "Kann Spuren von Verrat enthalten",
      "FUNNY_TAGLINE_26": "Gaslighting deiner Freunde, verantwortungsvoll",
      "FUNNY_TAGLINE_27": "Niemand mag einen schlechten Lügner. Verbessere dich.",
      "FUNNY_TAGLINE_28": "Schwitzen? Wahrscheinlich der Verräter.",
      "FUNNY_TAGLINE_29": "Lügen schmecken besser, wenn Freunde dabei sind",
      "FUNNY_TAGLINE_30": "Warnung: dein Pokerface ist schrecklich",
      "CUSTOM_COMMA_HINT": "Mit Kommas trennen · mindestens 1 Thema",
      "PASS_AND_PLAY": "Weitergeben & Spielen",
      "LOCAL_MULTIPLAYER": "Lokaler Mehrspieler",
      "LAN_CONNECT_HINT": "Spieler im selben WLAN oder Bluetooth-Hotspot",
      "LAN_HOST_BUTTON": "Spiel erstellen",
      "LAN_HOST_DESC": "Spiel auf diesem Gerät starten. Andere treten per IP bei.",
      "LAN_JOIN_BUTTON": "Spiel beitreten",
      "LAN_JOIN_DESC": "Spiel automatisch finden oder Host-IP eingeben.",
      "LAN_HOST_TITLE": "Spiel läuft",
      "LAN_HOST_IP_LABEL": "Deine IP-Adresse:",
      "LAN_HOST_WAITING": "Warte auf Spieler...",
      "LAN_HOST_START_GAME": "Spiel starten",
      "LAN_HOST_MIN_PLAYERS": "Mindestens 3 Spieler nötig",
      "LAN_JOIN_TITLE": "Spiel beitreten",
      "LAN_JOIN_AUTO_LABEL": "Gefundene Spiele in der Nähe",
      "LAN_JOIN_SCANNING": "Suche nach Spielen...",
      "LAN_JOIN_IP_HINT": "Oder Host-IP manuell eingeben",
      "LAN_JOIN_CONNECT": "Verbinden",
      "LAN_JOIN_CONNECTING": "Verbinde...",
      "LAN_JOIN_WAITING": "Verbunden! Warte auf Spielstart...",
      "LAN_JOIN_FAILED": "Verbindung fehlgeschlagen. IP prüfen und erneut versuchen.",
      "LAN_AVATAR_TITLE": "Avatar wählen",
      "LAN_AVATAR_CONFIRM": "Bestätigen",
      "LAN_AVATAR_READY_COUNT": "{ready} / {total} bereit",
      "LAN_ROLE_REVEAL_TITLE": "Deine Rolle",
      "LAN_ROLE_WAITING": "Warte auf alle Spieler...",
      "LAN_QUESTIONS_HOST_HINT": "Weiter tippen um voranzukommen",
      "LAN_QUESTIONS_CLIENT_HINT": "Host steuert die Fragen",
      "LAN_VOTES_COUNT": "Stimmen: {count} / {total}",
      "LAN_REVEAL_CLIENT_WAIT": "Warte auf Weiter des Hosts...",
      "LAN_GUESS_WAITING": "Der Imposter denkt nach...",
      "LAN_SUMMARY_CLIENT_WAIT": "Warte auf Host...",
      "IMPOSTER_FLED_TITLE": "Der Imposter ist geflohen!",
      "IMPOSTER_FLED_MESSAGE": "{name} ist wie ein Feigling geflohen! Alle bekommen 100 Punkte!",
      "HOST_LEFT_MESSAGE": "Der Host hat das Spiel verlassen.",
      "QUIT_CONFIRM_LAN": "Multiplayer-Spiel verlassen? Andere Spieler werden betroffen.",
      "LAN_NAME_LABEL": "Dein Name",
      "LAN_BLUETOOTH_TIP": "Kein WLAN? Bluetooth-Hotspot auf einem Gerät aktivieren.",
      "CONFIRM_VOTE": "Stimme bestätigen",
      "CANCEL": "Abbrechen",
      "YES_FINISH": "Ja, beenden",
      "KEEP_THIS": "Schnelligkeitsbonus gespeichert",
      "CONFIRM_END_GAME": "Spiel beenden?",
      "ROUND_BONUS": "Rundenbonus",
      "BONUS_ALL_PLAYERS": "{delta} Punkte für ALLE!",
      "BONUS_FROM_ROUND": "Bonus: {delta} Pkt",
      "LOADING_IMAGE": "Bild wird geladen...",
      "TAP_TO_CLOSE": "Tippe irgendwo um zu schließen",
      "HOW_STEP6_TITLE": "Schnelligkeitsbonus",
      "HOW_STEP6_DESC": "Ein ⚡500-Punkte-Pool schwindet bei der Diskussion. Schneller fertig = mehr Bonus für Nicht-Impostors!",
      "HOW_STEP8_TITLE": "Glücksrad",
      "HOW_STEP8_DESC": "Vor jeder Punktetabelle dreht der Automat für ALLE! Gewinn (60%): +50 Pkt. Verlust (40%): −50 Pkt. Minimum immer 0."
    }
  },
  "fr": {
    "translation": {
      "GAME_TITLE": "L'Imposteur",
      "TAGLINE": "Qui est parmi nous ?",
      "LANGUAGE_SELECT": "Choisir la langue",
      "NEW_GAME": "Nouveau jeu",
      "HOW_TO_PLAY": "Comment jouer",
      "HOW_TITLE": "Comment jouer",
      "HOW_STEP1_TITLE": "Installation",
      "HOW_STEP1_DESC": "Entrez 3 à 8 noms et choisissez une catégorie.",
      "HOW_STEP2_TITLE": "Révéler les rôles",
      "HOW_STEP2_DESC": "Passez le téléphone à chaque joueur. L'imposteur ne voit pas le sujet !",
      "HOW_STEP3_TITLE": "Poser des questions",
      "HOW_STEP3_DESC": "Les joueurs se posent des questions Oui/Non sur le sujet. L'imposteur bluffe !",
      "HOW_STEP4_TITLE": "Voter",
      "HOW_STEP4_DESC": "Tout le monde vote secrètement pour qui il pense être l'imposteur. Vous ne pouvez pas voter pour vous-même — sauf en mode difficile !",
      "HOW_STEP5_TITLE": "Score",
      "HOW_STEP5_DESC": "Deviner l'imposteur = +100 pts. L'imposteur devine le sujet = +100 pts. Trompe tout le monde = +200 bonus (mode normal uniquement). Mode difficile : vote sur soi = +100 pts ; pas de bonus de tromperie.",
      "BACK": "Retour",
      "CONTINUE": "Continuer",
      "DONE": "Compris !",
      "SETUP_TITLE": "Configuration",
      "ADD_PLAYER": "+ Ajouter joueur",
      "REMOVE_PLAYER": "Supprimer dernier",
      "PLAYER_N": "Joueur {n}",
      "PLAYER_NAME_HINT": "Nom du joueur...",
      "PLAYERS_LABEL": "Joueurs ({count})",
      "MIN_PLAYERS_WARNING": "Il faut au moins 3 joueurs !",
      "EMPTY_NAME_WARNING": "Tous les noms de joueurs doivent être remplis !",
      "DUPLICATE_NAME_WARNING": "Deux joueurs ne peuvent pas avoir le même nom !",
      "HARD_MODE": "Mode difficile",
      "HARD_MODE_HINT": "L'imposteur voit un faux sujet — personne ne sait qui il est !",
      "SELECT_CATEGORY": "Choisir une catégorie",
      "START_GAME": "Démarrer le jeu !",
      "PASS_TO": "Passez à {name}",
      "TAP_TO_REVEAL": "Appuyez pour voir votre rôle",
      "PLAYER_X_OF_Y": "Joueur {current} sur {total}",
      "PRIVACY_NOTE": "Ne montrez pas aux autres !",
      "YOU_ARE_IMPOSTER": "Tu es\nL'IMPOSTEUR !",
      "IMPOSTER_DESCRIPTION": "Tu ne connais pas le sujet. Pose des questions intelligentes sans te faire démasquer !",
      "YOU_KNOW_SUBJECT": "Le sujet est :",
      "REMEMBER_SUBJECT": "Mémorises-le ! Ne le dis pas à voix haute.",
      "QUESTION_PHASE_TITLE": "Temps des questions",
      "QUESTION_COUNT": "Question {current} sur {total}",
      "PLAYER_ASKS": "{asker} interroge {answerer}",
      "ASK_INSTRUCTIONS": "Posez une question Oui/Non sur le sujet",
      "NEXT_QUESTION": "Question suivante",
      "FINISH_QUESTIONS": "Fin des questions & Vote",
      "VOTING_TITLE": "Votez pour l'imposteur",
      "VOTING_PLAYER": "{name}, qui est l'imposteur ?",
      "VOTING_INSTRUCTIONS": "Qui est l'imposteur ? Tapez son nom pour voter !",
      "VOTE_SUBMIT": "Voter",
      "REVEAL_TITLE": "L'imposteur est…",
      "CORRECT_VOTERS": "Ont deviné juste",
      "INCORRECT_VOTERS": "Trompés par l'imposteur",
      "NOBODY_GUESSED": "Personne n'a trouvé l'imposteur ! +200 bonus !",
      "GUESS_TITLE": "Dernier défi de l'imposteur",
      "PASS_TO_IMPOSTER": "Passez à {name} (l'imposteur)",
      "GUESS_INSTRUCTIONS": "Quel était le sujet dont tout le monde parlait ?",
      "SUBMIT_GUESS": "Soumettre ma réponse",
      "GUESS_CORRECT": "Correct ! +100 points !",
      "GUESS_WRONG": "Faux ! Le sujet était : {subject}",
      "SUMMARY_TITLE": "Résumé de la manche {round}",
      "SCORES_TITLE": "Classement",
      "NEXT_ROUND": "Tour suivant",
      "END_GAME": "Terminer le jeu",
      "WINNER_IS": "En tête : {name}",
      "CAT_RANDOM": "🎲 Aléatoire",
      "CAT_FOOD": "🍕 Nourriture",
      "CAT_ANIMALS": "🦁 Animaux",
      "CAT_COUNTRIES": "🌍 Pays",
      "CAT_SPORTS": "⚽ Sports",
      "CAT_VEHICLES": "✈️ Véhicules",
      "CAT_CLOTHING": "👗 Vêtements",
      "CAT_NATURE": "🌈 Nature",
      "CAT_MOVIES": "🎬 Films",
      "CAT_MUSIC": "🎵 Musique",
      "CAT_CUSTOM": "✏️ Personnalisé",
      "SETTINGS": "Paramètres",
      "MUSIC_ON": "♫ Musique: ON",
      "MUSIC_OFF": "✕ Musique: OFF",
      "CUSTOM_SUBJECTS_HINT": "pomme, voiture, guitare, ...",
      "CUSTOM_MIN_WARNING": "Entrez au moins 1 sujet !",
      "LOADING_OPTIONS": "Recherche d'options…",
      "SAVED_GAME_FOUND": "Partie en cours",
      "RESUME_ROUND_INFO": "Manche {round} · {players} joueurs",
      "RESUME_GAME": "▶  Reprendre",
      "START_FRESH": "Nouveau jeu",
      "CREDITS": "Crédits",
      "QUIT_GAME": "Quitter",
      "QUIT_CONFIRM": "Terminer la partie en cours et recommencer ?",
      "KEEP_PLAYING": "Continuer",
      "ASKS_ARROW": "▼  demande  ▼",
      "FUNNY_TAGLINE_1": "Attention : peut causer des problèmes de confiance",
      "FUNNY_TAGLINE_2": "Tes amis mentent probablement",
      "FUNNY_TAGLINE_3": "Personne n'est innocent ici",
      "FUNNY_TAGLINE_4": "Suspicion garantie",
      "FUNNY_TAGLINE_5": "Amitiés testées depuis 2025",
      "FUNNY_TAGLINE_6": "L'imposteur est en train de lire ceci",
      "FUNNY_TAGLINE_7": "Accusations inventées à 100%",
      "FUNNY_TAGLINE_8": "Accuse quelqu'un. N'importe qui.",
      "FUNNY_TAGLINE_9": "Même l'hôte est suspect",
      "FUNNY_TAGLINE_10": "Pointe du doigt. Détruis les amitiés.",
      "FUNNY_TAGLINE_11": "Effets secondaires : paranoia et sueurs froides",
      "FUNNY_TAGLINE_12": "Aucune amitié n'a été blessée dans ce jeu... peut-être",
      "FUNNY_TAGLINE_13": "Sponsor officiel des silences gênants",
      "FUNNY_TAGLINE_14": "Contact visuel = suspicion instantanée",
      "FUNNY_TAGLINE_15": "Le silencieux l'a fait. Toujours.",
      "FUNNY_TAGLINE_16": "Visage impassible requis. Les résultats peuvent varier.",
      "FUNNY_TAGLINE_17": "Scientifiquement prouvé pour ruiner les soirées jeu",
      "FUNNY_TAGLINE_18": "Ne fais confiance à personne. Pas même à toi-même.",
      "FUNNY_TAGLINE_19": "Mentir : la seule compétence qui compte ici",
      "FUNNY_TAGLINE_20": "Rebondissement à venir. Chaque. Manche.",
      "FUNNY_TAGLINE_21": "Ton visage te trahit",
      "FUNNY_TAGLINE_22": "L'imposteur a déjà gagné le concours de regards",
      "FUNNY_TAGLINE_23": "Parrainé par des problèmes de confiance à 4h du matin",
      "FUNNY_TAGLINE_24": "L'accusation, c'est juste de l'honnêteté avec des étapes supplémentaires",
      "FUNNY_TAGLINE_25": "Peut contenir des traces de trahison",
      "FUNNY_TAGLINE_26": "Gaslighter vos amis, de façon responsable",
      "FUNNY_TAGLINE_27": "Personne n'aime un mauvais menteur. Améliore-toi.",
      "FUNNY_TAGLINE_28": "Tu transpires ? Probablement l'imposteur.",
      "FUNNY_TAGLINE_29": "Les mensonges ont meilleur goût avec des amis",
      "FUNNY_TAGLINE_30": "Attention : ton visage impassible est terrible",
      "CUSTOM_COMMA_HINT": "Séparer par des virgules · au moins 1 sujet",
      "PASS_AND_PLAY": "Passer & Jouer",
      "LOCAL_MULTIPLAYER": "Multi Local",
      "LAN_CONNECT_HINT": "Jouez ensemble sur le même WiFi ou hotspot Bluetooth",
      "LAN_HOST_BUTTON": "Héberger une partie",
      "LAN_HOST_DESC": "Démarrez une partie sur cet appareil. Les autres rejoignent via IP.",
      "LAN_JOIN_BUTTON": "Rejoindre une partie",
      "LAN_JOIN_DESC": "Trouvez une partie proche ou entrez l'IP de l'hôte.",
      "LAN_HOST_TITLE": "Hébergement en cours",
      "LAN_HOST_IP_LABEL": "Votre adresse IP :",
      "LAN_HOST_WAITING": "En attente de joueurs...",
      "LAN_HOST_START_GAME": "Démarrer la partie",
      "LAN_HOST_MIN_PLAYERS": "Minimum 3 joueurs requis",
      "LAN_JOIN_TITLE": "Rejoindre",
      "LAN_JOIN_AUTO_LABEL": "Parties trouvées à proximité",
      "LAN_JOIN_SCANNING": "Recherche de parties...",
      "LAN_JOIN_IP_HINT": "Ou entrez l'IP de l'hôte manuellement",
      "LAN_JOIN_CONNECT": "Connecter",
      "LAN_JOIN_CONNECTING": "Connexion...",
      "LAN_JOIN_WAITING": "Connecté ! En attente du démarrage...",
      "LAN_JOIN_FAILED": "Connexion échouée. Vérifiez l'IP et réessayez.",
      "LAN_AVATAR_TITLE": "Choisissez votre avatar",
      "LAN_AVATAR_CONFIRM": "Confirmer",
      "LAN_AVATAR_READY_COUNT": "{ready} / {total} prêt",
      "LAN_ROLE_REVEAL_TITLE": "Votre rôle",
      "LAN_ROLE_WAITING": "En attente de tous les joueurs...",
      "LAN_QUESTIONS_HOST_HINT": "Appuyez sur Suivant",
      "LAN_QUESTIONS_CLIENT_HINT": "L'hôte contrôle les questions",
      "LAN_VOTES_COUNT": "Votes : {count} / {total}",
      "LAN_REVEAL_CLIENT_WAIT": "En attente de l'hôte...",
      "LAN_GUESS_WAITING": "L'imposteur réfléchit...",
      "LAN_SUMMARY_CLIENT_WAIT": "En attente de l'hôte...",
      "IMPOSTER_FLED_TITLE": "L'imposteur s'est enfui !",
      "IMPOSTER_FLED_MESSAGE": "{name} a fui comme un lâche ! Tout le monde gagne 100 points !",
      "HOST_LEFT_MESSAGE": "L'hôte a quitté la partie.",
      "QUIT_CONFIRM_LAN": "Quitter la partie multijoueur ? Les autres joueurs seront affectés.",
      "LAN_NAME_LABEL": "Votre nom",
      "LAN_BLUETOOTH_TIP": "Pas de WiFi ? Activez le hotspot Bluetooth sur un appareil.",
      "CONFIRM_VOTE": "Confirmer le vote",
      "CANCEL": "Annuler",
      "YES_FINISH": "Oui, terminer",
      "KEEP_THIS": "Bonus vitesse sauvegardé",
      "CONFIRM_END_GAME": "Terminer le jeu ?",
      "ROUND_BONUS": "Bonus de manche",
      "BONUS_ALL_PLAYERS": "{delta} pts pour TOUS !",
      "BONUS_FROM_ROUND": "Bonus: {delta} pts",
      "LOADING_IMAGE": "Chargement de l'image...",
      "TAP_TO_CLOSE": "Toucher n'importe où pour fermer",
      "HOW_STEP6_TITLE": "Bonus de rapidité",
      "HOW_STEP6_DESC": "Un pool de ⚡500 pts se vide pendant la discussion. Finissez plus vite pour garder plus de bonus — partagé entre les non-imposteurs !",
      "HOW_STEP8_TITLE": "Tour de chance",
      "HOW_STEP8_DESC": "Avant chaque tableau, la machine à sous tourne pour TOUS ! Gagner (60%) : +50 pts. Perdre (40%) : −50 pts. Minimum toujours 0."
    }
  },
  "pt": {
    "translation": {
      "GAME_TITLE": "O Impostor",
      "TAGLINE": "Quem é o impostor?",
      "LANGUAGE_SELECT": "Selecionar idioma",
      "NEW_GAME": "Novo jogo",
      "HOW_TO_PLAY": "Como jogar",
      "HOW_TITLE": "Como jogar",
      "HOW_STEP1_TITLE": "Configuração",
      "HOW_STEP1_DESC": "Digite 3-8 nomes e escolha uma categoria.",
      "HOW_STEP2_TITLE": "Revelar papéis",
      "HOW_STEP2_DESC": "Passe o celular para cada jogador. O impostor NÃO vê o tema!",
      "HOW_STEP3_TITLE": "Fazer perguntas",
      "HOW_STEP3_DESC": "Os jogadores se fazem perguntas Sim/Não sobre o tema. O impostor blefa!",
      "HOW_STEP4_TITLE": "Votar",
      "HOW_STEP4_DESC": "Todos votam secretamente em quem acham ser o impostor. Você não pode votar em si mesmo — exceto no modo difícil!",
      "HOW_STEP5_TITLE": "Pontuação",
      "HOW_STEP5_DESC": "Adivinhar o impostor = +100 pts. Impostor adivinha o tema = +100 pts. Engana todos = +200 bônus (modo normal apenas). Modo difícil: auto-voto = +100 pts; sem bônus de enganar.",
      "BACK": "Voltar",
      "CONTINUE": "Continuar",
      "DONE": "Entendido!",
      "SETUP_TITLE": "Configurar jogo",
      "ADD_PLAYER": "+ Adicionar jogador",
      "REMOVE_PLAYER": "Remover último",
      "PLAYER_N": "Jogador {n}",
      "PLAYER_NAME_HINT": "Nome do jogador...",
      "PLAYERS_LABEL": "Jogadores ({count})",
      "MIN_PLAYERS_WARNING": "Precisa de pelo menos 3 jogadores!",
      "EMPTY_NAME_WARNING": "Todos os nomes devem ser preenchidos!",
      "DUPLICATE_NAME_WARNING": "Dois jogadores não podem ter o mesmo nome!",
      "HARD_MODE": "Modo difícil",
      "HARD_MODE_HINT": "O impostor vê um tema falso — ninguém sabe quem é!",
      "SELECT_CATEGORY": "Escolher categoria",
      "START_GAME": "Iniciar jogo!",
      "PASS_TO": "Passe para {name}",
      "TAP_TO_REVEAL": "Toque para ver seu papel",
      "PLAYER_X_OF_Y": "Jogador {current} de {total}",
      "PRIVACY_NOTE": "Não mostre para os outros!",
      "YOU_ARE_IMPOSTER": "Você é\no IMPOSTOR!",
      "IMPOSTER_DESCRIPTION": "Você não sabe o tema. Faça perguntas inteligentes e não seja descoberto!",
      "YOU_KNOW_SUBJECT": "O tema é:",
      "REMEMBER_SUBJECT": "Lembre-se! Não fale em voz alta.",
      "QUESTION_PHASE_TITLE": "Hora das perguntas",
      "QUESTION_COUNT": "Pergunta {current} de {total}",
      "PLAYER_ASKS": "{asker} pergunta a {answerer}",
      "ASK_INSTRUCTIONS": "Faça uma pergunta Sim/Não sobre o tema",
      "NEXT_QUESTION": "Próxima pergunta",
      "FINISH_QUESTIONS": "Encerrar perguntas & Votar",
      "VOTING_TITLE": "Vote no impostor",
      "VOTING_PLAYER": "{name}, quem é o impostor?",
      "VOTING_INSTRUCTIONS": "Quem é o impostor? Toque no nome para votar!",
      "VOTE_SUBMIT": "Votar",
      "REVEAL_TITLE": "O impostor é…",
      "CORRECT_VOTERS": "Identificaram corretamente",
      "INCORRECT_VOTERS": "Enganados pelo impostor",
      "NOBODY_GUESSED": "Ninguém pegou o impostor! +200 bônus!",
      "GUESS_TITLE": "Última chance do impostor",
      "PASS_TO_IMPOSTER": "Passe para {name} (o impostor)",
      "GUESS_INSTRUCTIONS": "Qual era o tema sobre o qual todos estavam falando?",
      "SUBMIT_GUESS": "Enviar palpite",
      "GUESS_CORRECT": "Correto! +100 pontos!",
      "GUESS_WRONG": "Errado! O tema era: {subject}",
      "SUMMARY_TITLE": "Resumo da rodada {round}",
      "SCORES_TITLE": "Placar",
      "NEXT_ROUND": "Próxima rodada",
      "END_GAME": "Encerrar jogo",
      "WINNER_IS": "Na liderança: {name}",
      "CAT_RANDOM": "🎲 Aleatório",
      "CAT_FOOD": "🍕 Comida",
      "CAT_ANIMALS": "🦁 Animais",
      "CAT_COUNTRIES": "🌍 Países",
      "CAT_SPORTS": "⚽ Esportes",
      "CAT_VEHICLES": "✈️ Veículos",
      "CAT_CLOTHING": "👗 Roupas",
      "CAT_NATURE": "🌈 Natureza",
      "CAT_MOVIES": "🎬 Filmes",
      "CAT_MUSIC": "🎵 Música",
      "CAT_CUSTOM": "✏️ Personalizado",
      "SETTINGS": "Configurações",
      "MUSIC_ON": "♫ Música: ON",
      "MUSIC_OFF": "✕ Música: OFF",
      "CUSTOM_SUBJECTS_HINT": "maçã, carro, guitarra, ...",
      "CUSTOM_MIN_WARNING": "Insira pelo menos 1 assunto!",
      "LOADING_OPTIONS": "Buscando opções…",
      "SAVED_GAME_FOUND": "Jogo em andamento",
      "RESUME_ROUND_INFO": "Rodada {round} · {players} jogadores",
      "RESUME_GAME": "▶  Retomar",
      "START_FRESH": "Novo jogo",
      "CREDITS": "Créditos",
      "QUIT_GAME": "Sair para o Menu",
      "QUIT_CONFIRM": "Encerrar o jogo atual e recomeçar?",
      "KEEP_PLAYING": "Continuar",
      "ASKS_ARROW": "▼  pergunta  ▼",
      "FUNNY_TAGLINE_1": "Aviso: pode causar problemas de confiança",
      "FUNNY_TAGLINE_2": "Seus amigos provavelmente estão mentindo",
      "FUNNY_TAGLINE_3": "Ninguém aqui é inocente",
      "FUNNY_TAGLINE_4": "Suspeita garantida",
      "FUNNY_TAGLINE_5": "Testando amizades desde 2025",
      "FUNNY_TAGLINE_6": "O impostor está lendo isso",
      "FUNNY_TAGLINE_7": "100% de acusações inventadas",
      "FUNNY_TAGLINE_8": "Culpe alguém. Qualquer um.",
      "FUNNY_TAGLINE_9": "Até o anfitrião é suspeito",
      "FUNNY_TAGLINE_10": "Aponte o dedo. Destrua amizades.",
      "FUNNY_TAGLINE_11": "Efeitos colaterais incluem paranoia e suores frios",
      "FUNNY_TAGLINE_12": "Nenhuma amizade foi prejudicada neste jogo... talvez",
      "FUNNY_TAGLINE_13": "Patrocinador oficial dos silêncios constrangedores",
      "FUNNY_TAGLINE_14": "Contato visual = suspeita imediata",
      "FUNNY_TAGLINE_15": "O quieto fez isso. Sempre.",
      "FUNNY_TAGLINE_16": "Cara de pau necessária. Resultados podem variar.",
      "FUNNY_TAGLINE_17": "Cientificamente comprovado para arruinar noites de jogo",
      "FUNNY_TAGLINE_18": "Não confie em ninguém. Nem em você mesmo.",
      "FUNNY_TAGLINE_19": "Mentir: a única habilidade que importa aqui",
      "FUNNY_TAGLINE_20": "Reviravolta chegando. Cada. Rodada.",
      "FUNNY_TAGLINE_21": "Sua cara está te entregando",
      "FUNNY_TAGLINE_22": "O impostor já ganhou o concurso de encarar",
      "FUNNY_TAGLINE_23": "Patrocinado por problemas de confiança das 4 da manhã",
      "FUNNY_TAGLINE_24": "Acusação é só honestidade com passos extras",
      "FUNNY_TAGLINE_25": "Pode conter traços de traição",
      "FUNNY_TAGLINE_26": "Manipulando seus amigos, com responsabilidade",
      "FUNNY_TAGLINE_27": "Ninguém gosta de um mentiroso ruim. Melhore.",
      "FUNNY_TAGLINE_28": "Suando? Provavelmente o impostor.",
      "FUNNY_TAGLINE_29": "Mentiras têm melhor sabor com amigos por perto",
      "FUNNY_TAGLINE_30": "Aviso: seu poker face é terrível",
      "CUSTOM_COMMA_HINT": "Separar por vírgulas · pelo menos 1 assunto",
      "PASS_AND_PLAY": "Passar & Jogar",
      "LOCAL_MULTIPLAYER": "Multijogador Local",
      "LAN_CONNECT_HINT": "Jogue junto no mesmo WiFi ou hotspot Bluetooth",
      "LAN_HOST_BUTTON": "Criar Jogo",
      "LAN_HOST_DESC": "Inicie um jogo neste dispositivo. Outros entram via IP.",
      "LAN_JOIN_BUTTON": "Entrar no Jogo",
      "LAN_JOIN_DESC": "Encontre um jogo ou insira o IP do host.",
      "LAN_HOST_TITLE": "Criando Jogo",
      "LAN_HOST_IP_LABEL": "Seu Endereço IP:",
      "LAN_HOST_WAITING": "Aguardando jogadores...",
      "LAN_HOST_START_GAME": "Iniciar Jogo",
      "LAN_HOST_MIN_PLAYERS": "Mínimo 3 jogadores para começar",
      "LAN_JOIN_TITLE": "Entrar no Jogo",
      "LAN_JOIN_AUTO_LABEL": "Jogos Encontrados",
      "LAN_JOIN_SCANNING": "Procurando jogos...",
      "LAN_JOIN_IP_HINT": "Ou insira o IP manualmente",
      "LAN_JOIN_CONNECT": "Conectar",
      "LAN_JOIN_CONNECTING": "Conectando...",
      "LAN_JOIN_WAITING": "Conectado! Aguardando host iniciar...",
      "LAN_JOIN_FAILED": "Falha na conexão. Verifique o IP e tente novamente.",
      "LAN_AVATAR_TITLE": "Escolha seu Avatar",
      "LAN_AVATAR_CONFIRM": "Confirmar",
      "LAN_AVATAR_READY_COUNT": "{ready} / {total} prontos",
      "LAN_ROLE_REVEAL_TITLE": "Seu Papel",
      "LAN_ROLE_WAITING": "Aguardando todos...",
      "LAN_QUESTIONS_HOST_HINT": "Toque em Próximo",
      "LAN_QUESTIONS_CLIENT_HINT": "Host controla as perguntas",
      "LAN_VOTES_COUNT": "Votos: {count} / {total}",
      "LAN_REVEAL_CLIENT_WAIT": "Aguardando host continuar...",
      "LAN_GUESS_WAITING": "O impostor está pensando...",
      "LAN_SUMMARY_CLIENT_WAIT": "Aguardando host...",
      "IMPOSTER_FLED_TITLE": "O Impostor Fugiu!",
      "IMPOSTER_FLED_MESSAGE": "{name} fugiu como um covarde! Todos ganham 100 pontos!",
      "HOST_LEFT_MESSAGE": "O host saiu do jogo.",
      "QUIT_CONFIRM_LAN": "Sair do jogo multijogador? Outros jogadores serão afetados.",
      "LAN_NAME_LABEL": "Seu Nome",
      "LAN_BLUETOOTH_TIP": "Sem WiFi? Ative o Hotspot Bluetooth em um dispositivo.",
      "CONFIRM_VOTE": "Confirmar voto",
      "CANCEL": "Cancelar",
      "YES_FINISH": "Sim, terminar",
      "KEEP_THIS": "Bônus de velocidade salvo",
      "CONFIRM_END_GAME": "Encerrar o jogo?",
      "ROUND_BONUS": "Bônus de rodada",
      "BONUS_ALL_PLAYERS": "{delta} pts para TODOS!",
      "BONUS_FROM_ROUND": "Bônus: {delta} pts",
      "LOADING_IMAGE": "Carregando imagem...",
      "TAP_TO_CLOSE": "Toque em qualquer lugar para fechar",
      "HOW_STEP6_TITLE": "Bônus de velocidade",
      "HOW_STEP6_DESC": "Um pool de ⚡500 pts se esvazia na discussão. Termine mais rápido para guardar mais bônus — dividido entre os não-impostores!",
      "HOW_STEP8_TITLE": "Giro da sorte",
      "HOW_STEP8_DESC": "Antes de cada placar, a caça-níqueis gira para TODOS! Ganhar (60%): +50 pts. Perder (40%): −50 pts. Mínimo sempre 0."
    }
  },
  "es": {
    "translation": {
      "GAME_TITLE": "El Impostor",
      "TAGLINE": "¿Quién está entre nosotros?",
      "LANGUAGE_SELECT": "Seleccionar idioma",
      "NEW_GAME": "Nuevo juego",
      "HOW_TO_PLAY": "Cómo jugar",
      "HOW_TITLE": "Cómo jugar",
      "HOW_STEP1_TITLE": "Configuración",
      "HOW_STEP1_DESC": "Ingresa 3-8 nombres y elige una categoría.",
      "HOW_STEP2_TITLE": "Revelar roles",
      "HOW_STEP2_DESC": "Pasa el teléfono a cada jugador. ¡El impostor NO ve el tema!",
      "HOW_STEP3_TITLE": "Hacer preguntas",
      "HOW_STEP3_DESC": "Los jugadores se hacen preguntas Sí/No sobre el tema. ¡El impostor farolea!",
      "HOW_STEP4_TITLE": "Votar",
      "HOW_STEP4_DESC": "Todos votan en secreto por quién creen que es el impostor. No puedes votar por ti mismo — ¡salvo en modo difícil!",
      "HOW_STEP5_TITLE": "Puntuación",
      "HOW_STEP5_DESC": "Adivinar al impostor = +100 pts. Impostor adivina el tema = +100 pts. Engaña a todos = +200 bonus (solo modo normal). Modo difícil: auto-voto = +100 pts; sin bonus de engaño.",
      "BACK": "Volver",
      "CONTINUE": "Continuar",
      "DONE": "¡Entendido!",
      "SETUP_TITLE": "Configurar juego",
      "ADD_PLAYER": "+ Agregar jugador",
      "REMOVE_PLAYER": "Eliminar último",
      "PLAYER_N": "Jugador {n}",
      "PLAYER_NAME_HINT": "Nombre del jugador...",
      "PLAYERS_LABEL": "Jugadores ({count})",
      "MIN_PLAYERS_WARNING": "¡Se necesitan al menos 3 jugadores!",
      "EMPTY_NAME_WARNING": "¡Todos los nombres deben ser completados!",
      "DUPLICATE_NAME_WARNING": "¡No puede haber dos jugadores con el mismo nombre!",
      "HARD_MODE": "Modo difícil",
      "HARD_MODE_HINT": "El impostor ve un tema falso — ¡nadie sabe quién es!",
      "SELECT_CATEGORY": "Elegir categoría",
      "START_GAME": "¡Iniciar juego!",
      "PASS_TO": "Pasa a {name}",
      "TAP_TO_REVEAL": "Toca para ver tu rol",
      "PLAYER_X_OF_Y": "Jugador {current} de {total}",
      "PRIVACY_NOTE": "¡No muestres a otros!",
      "YOU_ARE_IMPOSTER": "¡Eres\nel IMPOSTOR!",
      "IMPOSTER_DESCRIPTION": "No conoces el tema. ¡Haz preguntas inteligentes y no te descubran!",
      "YOU_KNOW_SUBJECT": "El tema es:",
      "REMEMBER_SUBJECT": "¡Recuérdalo! No lo digas en voz alta.",
      "QUESTION_PHASE_TITLE": "Tiempo de preguntas",
      "QUESTION_COUNT": "Pregunta {current} de {total}",
      "PLAYER_ASKS": "{asker} pregunta a {answerer}",
      "ASK_INSTRUCTIONS": "Haz una pregunta Sí/No sobre el tema",
      "NEXT_QUESTION": "Siguiente pregunta",
      "FINISH_QUESTIONS": "Terminar preguntas & Votar",
      "VOTING_TITLE": "Vota por el impostor",
      "VOTING_PLAYER": "{name}, ¿quién es el impostor?",
      "VOTING_INSTRUCTIONS": "¿Quién es el impostor? ¡Toca su nombre para votar!",
      "VOTE_SUBMIT": "Emitir voto",
      "REVEAL_TITLE": "El impostor es…",
      "CORRECT_VOTERS": "Identificaron correctamente",
      "INCORRECT_VOTERS": "Engañados por el impostor",
      "NOBODY_GUESSED": "¡Nadie atrapó al impostor! ¡+200 bonus!",
      "GUESS_TITLE": "Última oportunidad del impostor",
      "PASS_TO_IMPOSTER": "Pasa a {name} (el impostor)",
      "GUESS_INSTRUCTIONS": "¿Cuál era el tema del que todos hablaban?",
      "SUBMIT_GUESS": "Enviar respuesta",
      "GUESS_CORRECT": "¡Correcto! ¡+100 puntos!",
      "GUESS_WRONG": "¡Incorrecto! El tema era: {subject}",
      "SUMMARY_TITLE": "Resumen de la ronda {round}",
      "SCORES_TITLE": "Marcador",
      "NEXT_ROUND": "Siguiente ronda",
      "END_GAME": "Terminar juego",
      "WINNER_IS": "Liderando: {name}",
      "CAT_RANDOM": "🎲 Aleatorio",
      "CAT_FOOD": "🍕 Comida",
      "CAT_ANIMALS": "🦁 Animales",
      "CAT_COUNTRIES": "🌍 Países",
      "CAT_SPORTS": "⚽ Deportes",
      "CAT_VEHICLES": "✈️ Vehículos",
      "CAT_CLOTHING": "👗 Ropa",
      "CAT_NATURE": "🌈 Naturaleza",
      "CAT_MOVIES": "🎬 Películas",
      "CAT_MUSIC": "🎵 Música",
      "CAT_CUSTOM": "✏️ Personalizado",
      "SETTINGS": "Configuración",
      "MUSIC_ON": "♫ Música: ON",
      "MUSIC_OFF": "✕ Música: OFF",
      "CUSTOM_SUBJECTS_HINT": "manzana, coche, guitarra, ...",
      "CUSTOM_MIN_WARNING": "¡Introduce al menos 1 tema!",
      "LOADING_OPTIONS": "Buscando opciones…",
      "SAVED_GAME_FOUND": "Partida en curso",
      "RESUME_ROUND_INFO": "Ronda {round} · {players} jugadores",
      "RESUME_GAME": "▶  Reanudar",
      "START_FRESH": "Nuevo juego",
      "CREDITS": "Créditos",
      "QUIT_GAME": "Salir al Menú",
      "QUIT_CONFIRM": "¿Terminar la partida actual y volver a empezar?",
      "KEEP_PLAYING": "Seguir Jugando",
      "ASKS_ARROW": "▼  pregunta  ▼",
      "FUNNY_TAGLINE_1": "Advertencia: puede causar problemas de confianza",
      "FUNNY_TAGLINE_2": "Tus amigos probablemente mienten",
      "FUNNY_TAGLINE_3": "Nadie es inocente aquí",
      "FUNNY_TAGLINE_4": "Sospecha garantizada",
      "FUNNY_TAGLINE_5": "Amistades probadas desde 2025",
      "FUNNY_TAGLINE_6": "El impostor está leyendo esto",
      "FUNNY_TAGLINE_7": "100% de acusaciones inventadas",
      "FUNNY_TAGLINE_8": "Culpa a alguien. A quien sea.",
      "FUNNY_TAGLINE_9": "Hasta el anfitrión es sospechoso",
      "FUNNY_TAGLINE_10": "Señala con el dedo. Destruye amistades.",
      "FUNNY_TAGLINE_11": "Efectos secundarios incluyen paranoia y sudores fríos",
      "FUNNY_TAGLINE_12": "Ninguna amistad fue dañada en este juego... tal vez",
      "FUNNY_TAGLINE_13": "Patrocinador oficial de los silencios incómodos",
      "FUNNY_TAGLINE_14": "Contacto visual = sospecha instantánea",
      "FUNNY_TAGLINE_15": "El callado lo hizo. Siempre.",
      "FUNNY_TAGLINE_16": "Se requiere cara de póker. Los resultados pueden variar.",
      "FUNNY_TAGLINE_17": "Científicamente probado para arruinar noches de juego",
      "FUNNY_TAGLINE_18": "No confíes en nadie. Ni en ti mismo.",
      "FUNNY_TAGLINE_19": "Mentir: la única habilidad que importa aquí",
      "FUNNY_TAGLINE_20": "Giro de trama entrante. Cada. Ronda.",
      "FUNNY_TAGLINE_21": "Tu cara te está delatando",
      "FUNNY_TAGLINE_22": "El impostor ya ganó el concurso de miradas",
      "FUNNY_TAGLINE_23": "Patrocinado por problemas de confianza de las 4 AM",
      "FUNNY_TAGLINE_24": "Acusar es solo honestidad con pasos extra",
      "FUNNY_TAGLINE_25": "Puede contener trazas de traición",
      "FUNNY_TAGLINE_26": "Manipulando psicológicamente a tus amigos, responsablemente",
      "FUNNY_TAGLINE_27": "A nadie le gusta un mal mentiroso. Mejora.",
      "FUNNY_TAGLINE_28": "¿Sudando? Probablemente el impostor.",
      "FUNNY_TAGLINE_29": "Las mentiras saben mejor con amigos alrededor",
      "FUNNY_TAGLINE_30": "Advertencia: tu cara de póker es terrible",
      "CUSTOM_COMMA_HINT": "Separar con comas · al menos 1 tema",
      "PASS_AND_PLAY": "Pasar & Jugar",
      "LOCAL_MULTIPLAYER": "Multijugador Local",
      "LAN_CONNECT_HINT": "Juega juntos en el mismo WiFi o punto de acceso Bluetooth",
      "LAN_HOST_BUTTON": "Crear Partida",
      "LAN_HOST_DESC": "Inicia una partida en este dispositivo. Otros se unen por IP.",
      "LAN_JOIN_BUTTON": "Unirse a Partida",
      "LAN_JOIN_DESC": "Encuentra una partida automáticamente o ingresa el IP del host.",
      "LAN_HOST_TITLE": "Creando Partida",
      "LAN_HOST_IP_LABEL": "Tu dirección IP:",
      "LAN_HOST_WAITING": "Esperando jugadores...",
      "LAN_HOST_START_GAME": "Iniciar Partida",
      "LAN_HOST_MIN_PLAYERS": "Mínimo 3 jugadores para empezar",
      "LAN_JOIN_TITLE": "Unirse",
      "LAN_JOIN_AUTO_LABEL": "Partidas Encontradas",
      "LAN_JOIN_SCANNING": "Buscando partidas...",
      "LAN_JOIN_IP_HINT": "O ingresa el IP del host manualmente",
      "LAN_JOIN_CONNECT": "Conectar",
      "LAN_JOIN_CONNECTING": "Conectando...",
      "LAN_JOIN_WAITING": "Conectado! Esperando que el host inicie...",
      "LAN_JOIN_FAILED": "Error de conexión. Verifica el IP e inténtalo de nuevo.",
      "LAN_AVATAR_TITLE": "Elige tu Avatar",
      "LAN_AVATAR_CONFIRM": "Confirmar",
      "LAN_AVATAR_READY_COUNT": "{ready} / {total} listos",
      "LAN_ROLE_REVEAL_TITLE": "Tu Rol",
      "LAN_ROLE_WAITING": "Esperando a todos...",
      "LAN_QUESTIONS_HOST_HINT": "Toca Siguiente",
      "LAN_QUESTIONS_CLIENT_HINT": "El host controla las preguntas",
      "LAN_VOTES_COUNT": "Votos: {count} / {total}",
      "LAN_REVEAL_CLIENT_WAIT": "Esperando al host...",
      "LAN_GUESS_WAITING": "El impostor está pensando...",
      "LAN_SUMMARY_CLIENT_WAIT": "Esperando al host...",
      "IMPOSTER_FLED_TITLE": "¡El Impostor Escapó!",
      "IMPOSTER_FLED_MESSAGE": "¡{name} huyó como un cobarde! ¡Todos obtienen 100 puntos!",
      "HOST_LEFT_MESSAGE": "El host ha abandonado la partida.",
      "QUIT_CONFIRM_LAN": "¿Salir del juego multijugador? Afectará a otros jugadores.",
      "LAN_NAME_LABEL": "Tu Nombre",
      "LAN_BLUETOOTH_TIP": "¿Sin WiFi? Activa el hotspot Bluetooth en un dispositivo.",
      "CONFIRM_VOTE": "Confirmar voto",
      "CANCEL": "Cancelar",
      "YES_FINISH": "Sí, terminar",
      "KEEP_THIS": "Bono de velocidad guardado",
      "CONFIRM_END_GAME": "¿Terminar el juego?",
      "ROUND_BONUS": "Bono de ronda",
      "BONUS_ALL_PLAYERS": "¡{delta} pts para TODOS!",
      "BONUS_FROM_ROUND": "Bono: {delta} pts",
      "LOADING_IMAGE": "Cargando imagen...",
      "TAP_TO_CLOSE": "Toca en cualquier lugar para cerrar",
      "HOW_STEP6_TITLE": "Bono de velocidad",
      "HOW_STEP6_DESC": "Un pool de ⚡500 pts se drena mientras discuten. ¡Terminen rápido para guardar más bono — repartido entre los no impostores!",
      "HOW_STEP8_TITLE": "Giro de la suerte",
      "HOW_STEP8_DESC": "¡Antes de cada marcador, la máquina gira para TODOS! Ganar (60%): +50 pts. Perder (40%): −50 pts. Mínimo siempre 0."
    }
  }
}